[
  {
    "name": "卢卡-东契奇",
    "team": "湖人",
    "gp": 64,
    "mpg": 35.8,
    "得分": 33.5,
    "命中-出手": [
      10.8,
      22.8
    ],
    "命中率": 47.6,
    "命中-三分": [
      4.0,
      10.8
    ],
    "三分命中率": 36.6,
    "命中-罚球": [
      7.9,
      10.1
    ],
    "罚球命中率": 78.0,
    "上场时间": 35.8,
    "助攻数": 8.3,
    "失误数": 3.98,
    "助攻/失误": 2.09,
    "篮板数": 7.7,
    "进攻篮板": 0.6,
    "防守篮板": 7.1,
    "抢断数": 1.64,
    "犯规数": 2.39,
    "抢断/失误": 0.01,
    "抢断/犯规": 0.69,
    "pts": 33.5,
    "fgm": 10.8,
    "fga": 22.8,
    "fg_pct": 47.6,
    "tpm": 4.0,
    "tpa": 10.8,
    "tp_pct": 36.6,
    "ftm": 7.9,
    "fta": 10.1,
    "ft_pct": 78.0,
    "ast": 0.0,
    "reb": 0.0,
    "oreb": 0.0,
    "dreb": 0.0,
    "stl": 0.0,
    "blk": 0.0
  },
  {
    "name": "谢伊-吉尔杰斯-亚历山大",
    "team": "雷霆",
    "gp": 68,
    "mpg": 33.2,
    "得分": 31.1,
    "命中-出手": [
      10.8,
      19.4
    ],
    "命中率": 55.3,
    "命中-三分": [
      1.7,
      4.4
    ],
    "三分命中率": 38.6,
    "命中-罚球": [
      7.9,
      9.0
    ],
    "罚球命中率": 87.9,
    "上场时间": 33.2,
    "助攻数": 6.6,
    "失误数": 2.22,
    "助攻/失误": 2.97,
    "抢断数": 1.4,
    "犯规数": 2.04,
    "抢断/失误": 0.01,
    "抢断/犯规": 0.69,
    "盖帽数": 0.76,
    "盖帽/犯规": 0.37,
    "投篮命中率": 55.3,
    "调整命中率": 59.7,
    "命中-投篮": [
      10.8,
      19.4
    ],
    "三分命中数": 1.7,
    "三分出手数": 4.4,
    "罚球命中数": 7.9,
    "罚球出手数": 9.0,
    "pts": 31.1,
    "fgm": 10.8,
    "fga": 19.4,
    "fg_pct": 55.3,
    "tpm": 1.7,
    "tpa": 4.4,
    "tp_pct": 38.6,
    "ftm": 7.9,
    "fta": 9.0,
    "ft_pct": 87.9,
    "ast": 0.0,
    "reb": 0.0,
    "oreb": 0.0,
    "dreb": 0.0,
    "stl": 0.0,
    "blk": 0.0
  },
  {
    "name": "安东尼-爱德华兹",
    "team": "森林狼",
    "gp": 61,
    "mpg": 35.0,
    "得分": 28.8,
    "命中-出手": [
      9.9,
      20.2
    ],
    "命中率": 48.9,
    "命中-三分": [
      3.4,
      8.4
    ],
    "三分命中率": 39.9,
    "命中-罚球": [
      5.7,
      7.2
    ],
    "罚球命中率": 79.6,
    "上场时间": 35.0,
    "助攻数": 3.7,
    "失误数": 2.85,
    "助攻/失误": 1.3,
    "抢断数": 1.36,
    "犯规数": 1.93,
    "抢断/失误": 0.01,
    "抢断/犯规": 0.7,
    "盖帽数": 0.8,
    "盖帽/犯规": 0.41,
    "投篮命中率": 48.9,
    "调整命中率": 57.2,
    "命中-投篮": [
      9.9,
      20.2
    ],
    "三分命中数": 3.4,
    "三分出手数": 8.4,
    "pts": 28.8,
    "fgm": 9.9,
    "fga": 20.2,
    "fg_pct": 48.9,
    "tpm": 3.4,
    "tpa": 8.4,
    "tp_pct": 39.9,
    "ftm": 5.7,
    "fta": 7.2,
    "ft_pct": 79.6,
    "ast": 0.0,
    "reb": 0.0,
    "oreb": 0.0,
    "dreb": 0.0,
    "stl": 0.0,
    "blk": 0.0
  },
  {
    "name": "杰伦-布朗",
    "team": "凯尔特人",
    "gp": 71,
    "mpg": 34.4,
    "得分": 28.7,
    "命中-出手": [
      10.4,
      21.7
    ],
    "命中率": 47.7,
    "命中-三分": [
      2.0,
      5.7
    ],
    "三分命中率": 34.7,
    "命中-罚球": [
      6.0,
      7.6
    ],
    "罚球命中率": 79.5,
    "上场时间": 34.4,
    "助攻数": 5.1,
    "失误数": 3.65,
    "助攻/失误": 1.4,
    "篮板数": 6.9,
    "进攻篮板": 1.1,
    "防守篮板": 5.8,
    "pts": 28.7,
    "fgm": 10.4,
    "fga": 21.7,
    "fg_pct": 47.7,
    "tpm": 2.0,
    "tpa": 5.7,
    "tp_pct": 34.7,
    "ftm": 6.0,
    "fta": 7.6,
    "ft_pct": 79.5,
    "ast": 0.0,
    "reb": 0.0,
    "oreb": 0.0,
    "dreb": 0.0,
    "stl": 0.0,
    "blk": 0.0
  },
  {
    "name": "泰雷斯-马克西",
    "team": "76人",
    "gp": 70,
    "mpg": 38.0,
    "得分": 28.3,
    "命中-出手": [
      9.9,
      21.4
    ],
    "命中率": 46.2,
    "命中-三分": [
      3.1,
      8.6
    ],
    "三分命中率": 36.7,
    "命中-罚球": [
      5.3,
      6.0
    ],
    "罚球命中率": 89.2,
    "上场时间": 38.0,
    "助攻数": 6.6,
    "失误数": 2.44,
    "助攻/失误": 2.7,
    "抢断数": 1.86,
    "犯规数": 2.16,
    "抢断/失误": 0.01,
    "抢断/犯规": 0.86,
    "盖帽数": 0.79,
    "盖帽/犯规": 0.37,
    "罚球命中数": 5.3,
    "罚球出手数": 6.0,
    "pts": 28.3,
    "fgm": 9.9,
    "fga": 21.4,
    "fg_pct": 46.2,
    "tpm": 3.1,
    "tpa": 8.6,
    "tp_pct": 36.7,
    "ftm": 5.3,
    "fta": 6.0,
    "ft_pct": 89.2,
    "ast": 0.0,
    "reb": 0.0,
    "oreb": 0.0,
    "dreb": 0.0,
    "stl": 0.0,
    "blk": 0.0
  },
  {
    "name": "科怀-伦纳德",
    "team": "快船",
    "gp": 65,
    "mpg": 32.1,
    "得分": 27.9,
    "命中-出手": [
      9.8,
      19.4
    ],
    "命中率": 50.5,
    "命中-三分": [
      2.7,
      6.8
    ],
    "三分命中率": 38.7,
    "命中-罚球": [
      5.7,
      6.4
    ],
    "罚球命中率": 89.2,
    "上场时间": 32.1,
    "篮板数": 6.3,
    "进攻篮板": 1.1,
    "防守篮板": 5.3,
    "抢断数": 1.88,
    "失误数": 2.05,
    "犯规数": 1.2,
    "抢断/失误": 0.01,
    "抢断/犯规": 1.57,
    "投篮命中率": 50.5,
    "调整命中率": 57.3,
    "命中-投篮": [
      9.8,
      19.4
    ],
    "三分命中数": 2.7,
    "三分出手数": 6.8,
    "罚球命中数": 5.7,
    "罚球出手数": 6.4,
    "pts": 27.9,
    "fgm": 9.8,
    "fga": 19.4,
    "fg_pct": 50.5,
    "tpm": 2.7,
    "tpa": 6.8,
    "tp_pct": 38.7,
    "ftm": 5.7,
    "fta": 6.4,
    "ft_pct": 89.2,
    "ast": 0.0,
    "reb": 0.0,
    "oreb": 0.0,
    "dreb": 0.0,
    "stl": 0.0,
    "blk": 0.0
  },
  {
    "name": "多诺万-米切尔",
    "team": "骑士",
    "gp": 70,
    "mpg": 33.5,
    "得分": 27.9,
    "命中-出手": [
      9.7,
      20.0
    ],
    "命中率": 48.3,
    "命中-三分": [
      3.2,
      8.8
    ],
    "三分命中率": 36.4,
    "命中-罚球": [
      5.3,
      6.1
    ],
    "罚球命中率": 86.5,
    "上场时间": 33.5,
    "助攻数": 5.7,
    "失误数": 2.83,
    "助攻/失误": 2.01,
    "抢断数": 1.49,
    "犯规数": 2.33,
    "抢断/失误": 0.01,
    "抢断/犯规": 0.64,
    "罚球命中数": 5.3,
    "罚球出手数": 6.1,
    "pts": 27.9,
    "fgm": 9.7,
    "fga": 20.0,
    "fg_pct": 48.3,
    "tpm": 3.2,
    "tpa": 8.8,
    "tp_pct": 36.4,
    "ftm": 5.3,
    "fta": 6.1,
    "ft_pct": 86.5,
    "ast": 0.0,
    "reb": 0.0,
    "oreb": 0.0,
    "dreb": 0.0,
    "stl": 0.0,
    "blk": 0.0
  },
  {
    "name": "尼古拉-约基奇",
    "team": "掘金",
    "gp": 65,
    "mpg": 34.8,
    "得分": 27.7,
    "命中-出手": [
      9.9,
      17.4
    ],
    "命中率": 56.9,
    "命中-三分": [
      1.7,
      4.5
    ],
    "三分命中率": 38.0,
    "命中-罚球": [
      6.1,
      7.4
    ],
    "罚球命中率": 83.1,
    "上场时间": 34.8,
    "助攻数": 10.7,
    "失误数": 3.74,
    "助攻/失误": 2.86,
    "篮板数": 12.9,
    "进攻篮板": 3.0,
    "防守篮板": 9.9,
    "抢断数": 1.42,
    "犯规数": 2.66,
    "抢断/失误": 0.01,
    "抢断/犯规": 0.53,
    "盖帽数": 0.82,
    "盖帽/犯规": 0.31,
    "投篮命中率": 56.9,
    "调整命中率": 61.8,
    "命中-投篮": [
      9.9,
      17.4
    ],
    "罚球命中数": 6.1,
    "罚球出手数": 7.4,
    "pts": 27.7,
    "fgm": 9.9,
    "fga": 17.4,
    "fg_pct": 56.9,
    "tpm": 1.7,
    "tpa": 4.5,
    "tp_pct": 38.0,
    "ftm": 6.1,
    "fta": 7.4,
    "ft_pct": 83.1,
    "ast": 0.0,
    "reb": 0.0,
    "oreb": 0.0,
    "dreb": 0.0,
    "stl": 0.0,
    "blk": 0.0
  },
  {
    "name": "德文-布克",
    "team": "太阳",
    "gp": 64,
    "mpg": 33.5,
    "得分": 26.1,
    "命中-出手": [
      8.5,
      18.7
    ],
    "命中率": 45.6,
    "命中-三分": [
      1.9,
      5.8
    ],
    "三分命中率": 33.0,
    "命中-罚球": [
      7.1,
      8.1
    ],
    "罚球命中率": 87.3,
    "上场时间": 33.5,
    "助攻数": 6.0,
    "失误数": 3.14,
    "助攻/失误": 1.91,
    "罚球命中数": 7.1,
    "罚球出手数": 8.1,
    "pts": 26.1,
    "fgm": 8.5,
    "fga": 18.7,
    "fg_pct": 45.6,
    "tpm": 1.9,
    "tpa": 5.8,
    "tp_pct": 33.0,
    "ftm": 7.1,
    "fta": 8.1,
    "ft_pct": 87.3,
    "ast": 0.0,
    "reb": 0.0,
    "oreb": 0.0,
    "dreb": 0.0,
    "stl": 0.0,
    "blk": 0.0
  },
  {
    "name": "凯文-杜兰特",
    "team": "火箭",
    "gp": 78,
    "mpg": 36.4,
    "得分": 26.0,
    "命中-出手": [
      9.2,
      17.6
    ],
    "命中率": 52.0,
    "命中-三分": [
      2.4,
      5.8
    ],
    "三分命中率": 41.3,
    "命中-罚球": [
      5.2,
      6.0
    ],
    "罚球命中率": 87.4,
    "上场时间": 36.4,
    "助攻数": 4.8,
    "失误数": 3.15,
    "助攻/失误": 1.52,
    "盖帽数": 0.91,
    "犯规数": 1.82,
    "盖帽/犯规": 0.5,
    "投篮命中率": 52.0,
    "调整命中率": 58.8,
    "命中-投篮": [
      9.2,
      17.6
    ],
    "三分命中数": 2.4,
    "三分出手数": 5.8,
    "罚球命中数": 5.2,
    "罚球出手数": 6.0,
    "pts": 26.0,
    "fgm": 9.2,
    "fga": 17.6,
    "fg_pct": 52.0,
    "tpm": 2.4,
    "tpa": 5.8,
    "tp_pct": 41.3,
    "ftm": 5.2,
    "fta": 6.0,
    "ft_pct": 87.4,
    "ast": 0.0,
    "reb": 0.0,
    "oreb": 0.0,
    "dreb": 0.0,
    "stl": 0.0,
    "blk": 0.0
  },
  {
    "name": "杰伦-布伦森",
    "team": "尼克斯",
    "gp": 74,
    "mpg": 35.0,
    "得分": 26.0,
    "命中-出手": [
      9.3,
      19.9
    ],
    "命中率": 46.7,
    "命中-三分": [
      2.6,
      7.1
    ],
    "三分命中率": 36.9,
    "命中-罚球": [
      4.8,
      5.7
    ],
    "罚球命中率": 84.1,
    "上场时间": 35.0,
    "助攻数": 6.8,
    "失误数": 2.36,
    "助攻/失误": 2.88,
    "罚球命中数": 4.8,
    "罚球出手数": 5.7,
    "pts": 26.0,
    "fgm": 9.3,
    "fga": 19.9,
    "fg_pct": 46.7,
    "tpm": 2.6,
    "tpa": 7.1,
    "tp_pct": 36.9,
    "ftm": 4.8,
    "fta": 5.7,
    "ft_pct": 84.1,
    "ast": 0.0,
    "reb": 0.0,
    "oreb": 0.0,
    "dreb": 0.0,
    "stl": 0.0,
    "blk": 0.0
  },
  {
    "name": "贾马尔-默里",
    "team": "掘金",
    "gp": 75,
    "mpg": 35.4,
    "得分": 25.4,
    "命中-出手": [
      8.8,
      18.1
    ],
    "命中率": 48.3,
    "命中-三分": [
      3.3,
      7.5
    ],
    "三分命中率": 43.5,
    "命中-罚球": [
      4.6,
      5.2
    ],
    "罚球命中率": 88.7,
    "上场时间": 35.4,
    "助攻数": 7.1,
    "失误数": 2.28,
    "助攻/失误": 3.11,
    "三分命中数": 3.3,
    "三分出手数": 7.5,
    "罚球命中数": 4.6,
    "罚球出手数": 5.2,
    "pts": 25.4,
    "fgm": 8.8,
    "fga": 18.1,
    "fg_pct": 48.3,
    "tpm": 3.3,
    "tpa": 7.5,
    "tp_pct": 43.5,
    "ftm": 4.6,
    "fta": 5.2,
    "ft_pct": 88.7,
    "ast": 0.0,
    "reb": 0.0,
    "oreb": 0.0,
    "dreb": 0.0,
    "stl": 0.0,
    "blk": 0.0
  },
  {
    "name": "维克托·文班亚马",
    "team": "马刺",
    "gp": 64,
    "mpg": 29.2,
    "得分": 25.0,
    "命中-出手": [
      8.6,
      16.9
    ],
    "命中率": 51.2,
    "命中-三分": [
      1.9,
      5.5
    ],
    "三分命中率": 34.9,
    "命中-罚球": [
      5.8,
      7.0
    ],
    "罚球命中率": 82.7,
    "上场时间": 29.2,
    "篮板数": 11.5,
    "进攻篮板": 2.0,
    "防守篮板": 9.5,
    "盖帽数": 3.08,
    "犯规数": 2.44,
    "盖帽/犯规": 1.26,
    "投篮命中率": 51.2,
    "调整命中率": 56.8,
    "命中-投篮": [
      8.6,
      16.9
    ],
    "罚球命中数": 5.8,
    "罚球出手数": 7.0,
    "pts": 25.0,
    "fgm": 8.6,
    "fga": 16.9,
    "fg_pct": 51.2,
    "tpm": 1.9,
    "tpa": 5.5,
    "tp_pct": 34.9,
    "ftm": 5.8,
    "fta": 7.0,
    "ft_pct": 82.7,
    "ast": 0.0,
    "reb": 0.0,
    "oreb": 0.0,
    "dreb": 0.0,
    "stl": 0.0,
    "blk": 0.0
  },
  {
    "name": "德尼-阿夫迪亚",
    "team": "开拓者",
    "gp": 66,
    "mpg": 33.3,
    "得分": 24.2,
    "命中-出手": [
      7.5,
      16.1
    ],
    "命中率": 46.2,
    "命中-三分": [
      1.9,
      5.9
    ],
    "三分命中率": 31.8,
    "命中-罚球": [
      7.4,
      9.2
    ],
    "罚球命中率": 80.2,
    "上场时间": 33.3,
    "助攻数": 6.7,
    "失误数": 3.83,
    "助攻/失误": 1.75,
    "篮板数": 6.9,
    "进攻篮板": 1.1,
    "防守篮板": 5.8,
    "pts": 24.2,
    "fgm": 7.5,
    "fga": 16.1,
    "fg_pct": 46.2,
    "tpm": 1.9,
    "tpa": 5.9,
    "tp_pct": 31.8,
    "ftm": 7.4,
    "fta": 9.2,
    "ft_pct": 80.2,
    "ast": 0.0,
    "reb": 0.0,
    "oreb": 0.0,
    "dreb": 0.0,
    "stl": 0.0,
    "blk": 0.0
  },
  {
    "name": "帕斯卡尔-西亚卡姆",
    "team": "步行者",
    "gp": 62,
    "mpg": 33.2,
    "得分": 24.0,
    "命中-出手": [
      9.0,
      18.6
    ],
    "命中率": 48.4,
    "命中-三分": [
      1.7,
      4.7
    ],
    "三分命中率": 35.8,
    "命中-罚球": [
      4.2,
      6.1
    ],
    "罚球命中率": 69.3,
    "上场时间": 33.2,
    "助攻数": 3.8,
    "失误数": 2.23,
    "助攻/失误": 1.7,
    "篮板数": 6.6,
    "进攻篮板": 1.4,
    "防守篮板": 5.2,
    "pts": 24.0,
    "fgm": 9.0,
    "fga": 18.6,
    "fg_pct": 48.4,
    "tpm": 1.7,
    "tpa": 4.7,
    "tp_pct": 35.8,
    "ftm": 4.2,
    "fta": 6.1,
    "ft_pct": 69.3,
    "ast": 0.0,
    "reb": 0.0,
    "oreb": 0.0,
    "dreb": 0.0,
    "stl": 0.0,
    "blk": 0.0
  },
  {
    "name": "凯德-坎宁安",
    "team": "活塞",
    "gp": 64,
    "mpg": 33.9,
    "得分": 23.9,
    "命中-出手": [
      8.6,
      18.6
    ],
    "命中率": 46.1,
    "命中-三分": [
      2.0,
      5.7
    ],
    "三分命中率": 34.2,
    "命中-罚球": [
      4.8,
      6.0
    ],
    "罚球命中率": 81.2,
    "上场时间": 33.9,
    "助攻数": 9.9,
    "失误数": 3.69,
    "助攻/失误": 2.68,
    "抢断数": 1.44,
    "犯规数": 3.06,
    "抢断/失误": 0.01,
    "抢断/犯规": 0.47,
    "盖帽数": 0.84,
    "盖帽/犯规": 0.27,
    "pts": 23.9,
    "fgm": 8.6,
    "fga": 18.6,
    "fg_pct": 46.1,
    "tpm": 2.0,
    "tpa": 5.7,
    "tp_pct": 34.2,
    "ftm": 4.8,
    "fta": 6.0,
    "ft_pct": 81.2,
    "ast": 0.0,
    "reb": 0.0,
    "oreb": 0.0,
    "dreb": 0.0,
    "stl": 0.0,
    "blk": 0.0
  },
  {
    "name": "杰伦-约翰逊",
    "team": "老鹰",
    "gp": 72,
    "mpg": 35.2,
    "得分": 22.5,
    "命中-出手": [
      8.3,
      17.1
    ],
    "命中率": 48.9,
    "命中-三分": [
      1.7,
      4.7
    ],
    "三分命中率": 35.2,
    "命中-罚球": [
      4.2,
      5.3
    ],
    "罚球命中率": 78.8,
    "上场时间": 35.2,
    "助攻数": 7.9,
    "失误数": 3.39,
    "助攻/失误": 2.33,
    "篮板数": 10.3,
    "进攻篮板": 1.4,
    "防守篮板": 8.9,
    "抢断数": 1.24,
    "犯规数": 2.1,
    "抢断/失误": 0.01,
    "抢断/犯规": 0.59,
    "投篮命中率": 48.9,
    "调整命中率": 53.7,
    "命中-投篮": [
      8.3,
      17.1
    ],
    "pts": 22.5,
    "fgm": 8.3,
    "fga": 17.1,
    "fg_pct": 48.9,
    "tpm": 1.7,
    "tpa": 4.7,
    "tp_pct": 35.2,
    "ftm": 4.2,
    "fta": 5.3,
    "ft_pct": 78.8,
    "ast": 0.0,
    "reb": 0.0,
    "oreb": 0.0,
    "dreb": 0.0,
    "stl": 0.0,
    "blk": 0.0
  },
  {
    "name": "保罗-班切罗",
    "team": "魔术",
    "gp": 72,
    "mpg": 34.8,
    "得分": 22.2,
    "命中-出手": [
      7.3,
      16.0
    ],
    "命中率": 45.9,
    "命中-三分": [
      1.2,
      3.8
    ],
    "三分命中率": 30.5,
    "命中-罚球": [
      6.3,
      8.2
    ],
    "罚球命中率": 77.5,
    "上场时间": 34.8,
    "助攻数": 5.2,
    "失误数": 3.08,
    "助攻/失误": 1.69,
    "篮板数": 8.4,
    "进攻篮板": 1.2,
    "防守篮板": 7.2,
    "pts": 22.2,
    "fgm": 7.3,
    "fga": 16.0,
    "fg_pct": 45.9,
    "tpm": 1.2,
    "tpa": 3.8,
    "tp_pct": 30.5,
    "ftm": 6.3,
    "fta": 8.2,
    "ft_pct": 77.5,
    "ast": 0.0,
    "reb": 0.0,
    "oreb": 0.0,
    "dreb": 0.0,
    "stl": 0.0,
    "blk": 0.0
  },
  {
    "name": "诺曼-鲍威尔",
    "team": "热火",
    "gp": 58,
    "mpg": 29.6,
    "得分": 21.7,
    "命中-出手": [
      7.3,
      15.4
    ],
    "命中率": 47.0,
    "命中-三分": [
      2.7,
      7.1
    ],
    "三分命中率": 38.0,
    "命中-罚球": [
      4.5,
      5.5
    ],
    "罚球命中率": 82.7,
    "上场时间": 29.6,
    "罚球命中数": 4.5,
    "罚球出手数": 5.5,
    "pts": 21.7,
    "fgm": 7.3,
    "fga": 15.4,
    "fg_pct": 47.0,
    "tpm": 2.7,
    "tpa": 7.1,
    "tp_pct": 38.0,
    "ftm": 4.5,
    "fta": 5.5,
    "ft_pct": 82.7,
    "ast": 0.0,
    "reb": 0.0,
    "oreb": 0.0,
    "dreb": 0.0,
    "stl": 0.0,
    "blk": 0.0
  },
  {
    "name": "布兰登-英格拉姆",
    "team": "猛龙",
    "gp": 77,
    "mpg": 33.8,
    "得分": 21.5,
    "命中-出手": [
      8.0,
      16.7
    ],
    "命中率": 47.7,
    "命中-三分": [
      1.8,
      4.6
    ],
    "三分命中率": 38.2,
    "命中-罚球": [
      3.8,
      4.6
    ],
    "罚球命中率": 82.0,
    "上场时间": 33.8,
    "罚球命中数": 3.8,
    "罚球出手数": 4.6,
    "pts": 21.5,
    "fgm": 8.0,
    "fga": 16.7,
    "fg_pct": 47.7,
    "tpm": 1.8,
    "tpa": 4.6,
    "tp_pct": 38.2,
    "ftm": 3.8,
    "fta": 4.6,
    "ft_pct": 82.0,
    "ast": 0.0,
    "reb": 0.0,
    "oreb": 0.0,
    "dreb": 0.0,
    "stl": 0.0,
    "blk": 0.0
  },
  {
    "name": "特雷-墨菲",
    "team": "鹈鹕",
    "gp": 66,
    "mpg": 35.5,
    "得分": 21.5,
    "命中-出手": [
      7.5,
      15.9
    ],
    "命中率": 47.0,
    "命中-三分": [
      3.2,
      8.6
    ],
    "三分命中率": 37.9,
    "命中-罚球": [
      3.3,
      3.7
    ],
    "罚球命中率": 88.6,
    "上场时间": 35.5,
    "助攻数": 3.8,
    "失误数": 1.82,
    "助攻/失误": 2.09,
    "抢断数": 1.5,
    "犯规数": 2.09,
    "抢断/失误": 0.01,
    "抢断/犯规": 0.72,
    "罚球命中数": 3.3,
    "罚球出手数": 3.7,
    "pts": 21.5,
    "fgm": 7.5,
    "fga": 15.9,
    "fg_pct": 47.0,
    "tpm": 3.2,
    "tpa": 8.6,
    "tp_pct": 37.9,
    "ftm": 3.3,
    "fta": 3.7,
    "ft_pct": 88.6,
    "ast": 0.0,
    "reb": 0.0,
    "oreb": 0.0,
    "dreb": 0.0,
    "stl": 0.0,
    "blk": 0.0
  },
  {
    "name": "朱利叶斯-兰德尔",
    "team": "森林狼",
    "gp": 79,
    "mpg": 33.0,
    "得分": 21.1,
    "命中-出手": [
      7.3,
      15.3
    ],
    "命中率": 48.1,
    "命中-三分": [
      1.4,
      4.4
    ],
    "三分命中率": 31.5,
    "命中-罚球": [
      5.0,
      6.3
    ],
    "罚球命中率": 80.2,
    "上场时间": 33.0,
    "助攻数": 5.0,
    "失误数": 2.75,
    "助攻/失误": 1.82,
    "篮板数": 6.7,
    "进攻篮板": 1.7,
    "防守篮板": 5.1,
    "pts": 21.1,
    "fgm": 7.3,
    "fga": 15.3,
    "fg_pct": 48.1,
    "tpm": 1.4,
    "tpa": 4.4,
    "tp_pct": 31.5,
    "ftm": 5.0,
    "fta": 6.3,
    "ft_pct": 80.2,
    "ast": 0.0,
    "reb": 0.0,
    "oreb": 0.0,
    "dreb": 0.0,
    "stl": 0.0,
    "blk": 0.0
  },
  {
    "name": "蔡恩-威廉森",
    "team": "鹈鹕",
    "gp": 62,
    "mpg": 29.7,
    "得分": 21.0,
    "命中-出手": [
      7.8,
      13.0
    ],
    "命中率": 60.0,
    "命中-三分": [
      0.0,
      0.1
    ],
    "三分命中率": 25.0,
    "命中-罚球": [
      5.4,
      7.5
    ],
    "罚球命中率": 71.6,
    "上场时间": 29.7,
    "投篮命中率": 60.0,
    "调整命中率": 60.1,
    "命中-投篮": [
      7.8,
      13.0
    ],
    "pts": 21.0,
    "fgm": 7.8,
    "fga": 13.0,
    "fg_pct": 60.0,
    "tpm": 0.0,
    "tpa": 0.1,
    "tp_pct": 25.0,
    "ftm": 5.4,
    "fta": 7.5,
    "ft_pct": 71.6,
    "ast": 0.0,
    "reb": 0.0,
    "oreb": 0.0,
    "dreb": 0.0,
    "stl": 0.0,
    "blk": 0.0
  },
  {
    "name": "库珀-弗拉格",
    "team": "独行侠",
    "gp": 70,
    "mpg": 33.5,
    "得分": 21.0,
    "命中-出手": [
      8.0,
      17.1
    ],
    "命中率": 46.8,
    "命中-三分": [
      1.0,
      3.5
    ],
    "三分命中率": 29.5,
    "命中-罚球": [
      4.0,
      4.9
    ],
    "罚球命中率": 82.7,
    "上场时间": 33.5,
    "助攻数": 4.5,
    "失误数": 2.3,
    "助攻/失误": 1.96,
    "篮板数": 6.7,
    "进攻篮板": 1.2,
    "防守篮板": 5.4,
    "抢断数": 1.2,
    "犯规数": 2.03,
    "抢断/失误": 0.01,
    "抢断/犯规": 0.59,
    "盖帽数": 0.91,
    "盖帽/犯规": 0.45,
    "罚球命中数": 4.0,
    "罚球出手数": 4.9,
    "pts": 21.0,
    "fgm": 8.0,
    "fga": 17.1,
    "fg_pct": 46.8,
    "tpm": 1.0,
    "tpa": 3.5,
    "tp_pct": 29.5,
    "ftm": 4.0,
    "fta": 4.9,
    "ft_pct": 82.7,
    "ast": 0.0,
    "reb": 0.0,
    "oreb": 0.0,
    "dreb": 0.0,
    "stl": 0.0,
    "blk": 0.0
  },
  {
    "name": "勒布朗-詹姆斯",
    "team": "湖人",
    "gp": 60,
    "mpg": 33.2,
    "得分": 20.9,
    "命中-出手": [
      7.9,
      15.3
    ],
    "命中率": 51.5,
    "命中-三分": [
      1.3,
      4.1
    ],
    "三分命中率": 31.7,
    "命中-罚球": [
      3.9,
      5.3
    ],
    "罚球命中率": 73.7,
    "上场时间": 33.2,
    "助攻数": 7.2,
    "失误数": 2.98,
    "助攻/失误": 2.42,
    "篮板数": 6.1,
    "进攻篮板": 0.7,
    "防守篮板": 5.3,
    "抢断数": 1.2,
    "犯规数": 1.35,
    "抢断/失误": 0.01,
    "抢断/犯规": 0.89,
    "投篮命中率": 51.5,
    "调整命中率": 55.6,
    "命中-投篮": [
      7.9,
      15.3
    ],
    "pts": 20.9,
    "fgm": 7.9,
    "fga": 15.3,
    "fg_pct": 51.5,
    "tpm": 1.3,
    "tpa": 4.1,
    "tp_pct": 31.7,
    "ftm": 3.9,
    "fta": 5.3,
    "ft_pct": 73.7,
    "ast": 0.0,
    "reb": 0.0,
    "oreb": 0.0,
    "dreb": 0.0,
    "stl": 0.0,
    "blk": 0.0
  },
  {
    "name": "尼基尔-亚历山大-沃克",
    "team": "老鹰",
    "gp": 78,
    "mpg": 33.4,
    "得分": 20.8,
    "命中-出手": [
      7.0,
      15.3
    ],
    "命中率": 45.9,
    "命中-三分": [
      3.2,
      8.1
    ],
    "三分命中率": 39.9,
    "命中-罚球": [
      3.5,
      3.9
    ],
    "罚球命中率": 90.2,
    "上场时间": 33.4,
    "抢断数": 1.31,
    "失误数": 2.08,
    "犯规数": 2.22,
    "抢断/失误": 0.01,
    "抢断/犯规": 0.59,
    "三分命中数": 3.2,
    "三分出手数": 8.1,
    "罚球命中数": 3.5,
    "罚球出手数": 3.9,
    "pts": 20.8,
    "fgm": 7.0,
    "fga": 15.3,
    "fg_pct": 45.9,
    "tpm": 3.2,
    "tpa": 8.1,
    "tp_pct": 39.9,
    "ftm": 3.5,
    "fta": 3.9,
    "ft_pct": 90.2,
    "ast": 0.0,
    "reb": 0.0,
    "oreb": 0.0,
    "dreb": 0.0,
    "stl": 0.0,
    "blk": 0.0
  },
  {
    "name": "阿尔佩伦-申京",
    "team": "火箭",
    "gp": 72,
    "mpg": 33.3,
    "得分": 20.4,
    "命中-出手": [
      8.1,
      15.6
    ],
    "命中率": 51.9,
    "命中-三分": [
      0.6,
      1.8
    ],
    "三分命中率": 30.5,
    "命中-罚球": [
      3.6,
      5.2
    ],
    "罚球命中率": 69.1,
    "上场时间": 33.3,
    "助攻数": 6.2,
    "失误数": 3.15,
    "助攻/失误": 1.97,
    "篮板数": 8.9,
    "进攻篮板": 3.0,
    "防守篮板": 5.9,
    "抢断数": 1.18,
    "犯规数": 3.31,
    "抢断/失误": 0.01,
    "抢断/犯规": 0.36,
    "盖帽数": 1.07,
    "盖帽/犯规": 0.32,
    "投篮命中率": 51.9,
    "调整命中率": 53.7,
    "命中-投篮": [
      8.1,
      15.6
    ],
    "pts": 20.4,
    "fgm": 8.1,
    "fga": 15.6,
    "fg_pct": 51.9,
    "tpm": 0.6,
    "tpa": 1.8,
    "tp_pct": 30.5,
    "ftm": 3.6,
    "fta": 5.2,
    "ft_pct": 69.1,
    "ast": 0.0,
    "reb": 0.0,
    "oreb": 0.0,
    "dreb": 0.0,
    "stl": 0.0,
    "blk": 0.0
  },
  {
    "name": "布兰登·米勒",
    "team": "黄蜂",
    "gp": 65,
    "mpg": 30.3,
    "得分": 20.2,
    "命中-出手": [
      7.0,
      16.1
    ],
    "命中率": 43.5,
    "命中-三分": [
      3.1,
      8.2
    ],
    "三分命中率": 38.3,
    "命中-罚球": [
      3.1,
      3.4
    ],
    "罚球命中率": 89.2,
    "上场时间": 30.3,
    "三分命中数": 3.1,
    "三分出手数": 8.2,
    "罚球命中数": 3.1,
    "罚球出手数": 3.4,
    "pts": 20.2,
    "fgm": 7.0,
    "fga": 16.1,
    "fg_pct": 43.5,
    "tpm": 3.1,
    "tpa": 8.2,
    "tp_pct": 38.3,
    "ftm": 3.1,
    "fta": 3.4,
    "ft_pct": 89.2,
    "ast": 0.0,
    "reb": 0.0,
    "oreb": 0.0,
    "dreb": 0.0,
    "stl": 0.0,
    "blk": 0.0
  },
  {
    "name": "德斯蒙德-贝恩",
    "team": "魔术",
    "gp": 82,
    "mpg": 33.6,
    "得分": 20.1,
    "命中-出手": [
      7.1,
      14.7
    ],
    "命中率": 48.4,
    "命中-三分": [
      2.0,
      5.2
    ],
    "三分命中率": 39.1,
    "命中-罚球": [
      3.8,
      4.2
    ],
    "罚球命中率": 90.8,
    "上场时间": 33.6,
    "助攻数": 4.1,
    "失误数": 2.0,
    "助攻/失误": 2.05,
    "投篮命中率": 48.4,
    "调整命中率": 55.3,
    "命中-投篮": [
      7.1,
      14.7
    ],
    "三分命中数": 2.0,
    "三分出手数": 5.2,
    "罚球命中数": 3.8,
    "罚球出手数": 4.2,
    "pts": 20.1,
    "fgm": 7.1,
    "fga": 14.7,
    "fg_pct": 48.4,
    "tpm": 2.0,
    "tpa": 5.2,
    "tp_pct": 39.1,
    "ftm": 3.8,
    "fta": 4.2,
    "ft_pct": 90.8,
    "ast": 0.0,
    "reb": 0.0,
    "oreb": 0.0,
    "dreb": 0.0,
    "stl": 0.0,
    "blk": 0.0
  },
  {
    "name": "拉梅洛-鲍尔",
    "team": "黄蜂",
    "gp": 72,
    "mpg": 28.0,
    "得分": 20.1,
    "命中-出手": [
      7.0,
      17.3
    ],
    "命中率": 40.7,
    "命中-三分": [
      3.8,
      10.3
    ],
    "三分命中率": 36.8,
    "命中-罚球": [
      2.2,
      2.5
    ],
    "罚球命中率": 89.9,
    "上场时间": 28.0,
    "助攻数": 7.1,
    "失误数": 2.81,
    "助攻/失误": 2.53,
    "抢断数": 1.21,
    "犯规数": 2.71,
    "抢断/失误": 0.01,
    "抢断/犯规": 0.45,
    "罚球命中数": 2.2,
    "罚球出手数": 2.5,
    "pts": 20.1,
    "fgm": 7.0,
    "fga": 17.3,
    "fg_pct": 40.7,
    "tpm": 3.8,
    "tpa": 10.3,
    "tp_pct": 36.8,
    "ftm": 2.2,
    "fta": 2.5,
    "ft_pct": 89.9,
    "ast": 0.0,
    "reb": 0.0,
    "oreb": 0.0,
    "dreb": 0.0,
    "stl": 0.0,
    "blk": 0.0
  },
  {
    "name": "卡尔-安东尼-唐斯",
    "team": "尼克斯",
    "gp": 75,
    "mpg": 31.0,
    "得分": 20.1,
    "命中-出手": [
      6.9,
      13.8
    ],
    "命中率": 50.1,
    "命中-三分": [
      1.5,
      4.1
    ],
    "三分命中率": 36.8,
    "命中-罚球": [
      4.8,
      5.6
    ],
    "罚球命中率": 85.8,
    "上场时间": 31.0,
    "篮板数": 11.9,
    "进攻篮板": 3.1,
    "防守篮板": 8.8,
    "投篮命中率": 50.1,
    "调整命中率": 55.6,
    "命中-投篮": [
      6.9,
      13.8
    ],
    "罚球命中数": 4.8,
    "罚球出手数": 5.6,
    "pts": 20.1,
    "fgm": 6.9,
    "fga": 13.8,
    "fg_pct": 50.1,
    "tpm": 1.5,
    "tpa": 4.1,
    "tp_pct": 36.8,
    "ftm": 4.8,
    "fta": 5.6,
    "ft_pct": 85.8,
    "ast": 0.0,
    "reb": 0.0,
    "oreb": 0.0,
    "dreb": 0.0,
    "stl": 0.0,
    "blk": 0.0
  },
  {
    "name": "巴姆-阿德巴约",
    "team": "热火",
    "gp": 73,
    "mpg": 32.4,
    "得分": 20.1,
    "命中-出手": [
      6.9,
      15.7
    ],
    "命中率": 44.2,
    "命中-三分": [
      1.7,
      5.5
    ],
    "三分命中率": 31.8,
    "命中-罚球": [
      4.5,
      5.8
    ],
    "罚球命中率": 77.8,
    "上场时间": 32.4,
    "篮板数": 10.0,
    "进攻篮板": 2.0,
    "防守篮板": 8.0,
    "抢断数": 1.18,
    "失误数": 1.64,
    "犯规数": 1.67,
    "抢断/失误": 0.01,
    "抢断/犯规": 0.71,
    "pts": 20.1,
    "fgm": 6.9,
    "fga": 15.7,
    "fg_pct": 44.2,
    "tpm": 1.7,
    "tpa": 5.5,
    "tp_pct": 31.8,
    "ftm": 4.5,
    "fta": 5.8,
    "ft_pct": 77.8,
    "ast": 0.0,
    "reb": 0.0,
    "oreb": 0.0,
    "dreb": 0.0,
    "stl": 0.0,
    "blk": 0.0
  },
  {
    "name": "杰伦-杜伦",
    "team": "活塞",
    "gp": 70,
    "mpg": 28.2,
    "得分": 19.5,
    "命中-出手": [
      7.5,
      11.5
    ],
    "命中率": 65.0,
    "命中-三分": [
      0.0,
      0.0
    ],
    "三分命中率": 0.0,
    "命中-罚球": [
      4.6,
      6.1
    ],
    "罚球命中率": 74.7,
    "上场时间": 28.2,
    "篮板数": 10.5,
    "进攻篮板": 3.8,
    "防守篮板": 6.7,
    "盖帽数": 0.84,
    "犯规数": 2.79,
    "盖帽/犯规": 0.3,
    "投篮命中率": 65.0,
    "调整命中率": 65.0,
    "命中-投篮": [
      7.5,
      11.5
    ],
    "pts": 19.5,
    "fgm": 7.5,
    "fga": 11.5,
    "fg_pct": 65.0,
    "tpm": 0.0,
    "tpa": 0.0,
    "tp_pct": 0.0,
    "ftm": 4.6,
    "fta": 6.1,
    "ft_pct": 74.7,
    "ast": 0.0,
    "reb": 0.0,
    "oreb": 0.0,
    "dreb": 0.0,
    "stl": 0.0,
    "blk": 0.0
  },
  {
    "name": "达龙-福克斯",
    "team": "马刺",
    "gp": 72,
    "mpg": 31.0,
    "得分": 18.6,
    "命中-出手": [
      7.1,
      14.5
    ],
    "命中率": 48.6,
    "命中-三分": [
      1.8,
      5.5
    ],
    "三分命中率": 33.2,
    "命中-罚球": [
      2.6,
      3.4
    ],
    "罚球命中率": 76.0,
    "上场时间": 31.0,
    "助攻数": 6.2,
    "失误数": 2.28,
    "助攻/失误": 2.72,
    "抢断数": 1.24,
    "犯规数": 2.25,
    "抢断/失误": 0.01,
    "抢断/犯规": 0.55,
    "投篮命中率": 48.6,
    "调整命中率": 54.9,
    "命中-投篮": [
      7.1,
      14.5
    ],
    "pts": 18.6,
    "fgm": 7.1,
    "fga": 14.5,
    "fg_pct": 48.6,
    "tpm": 1.8,
    "tpa": 5.5,
    "tp_pct": 33.2,
    "ftm": 2.6,
    "fta": 3.4,
    "ft_pct": 76.0,
    "ast": 0.0,
    "reb": 0.0,
    "oreb": 0.0,
    "dreb": 0.0,
    "stl": 0.0,
    "blk": 0.0
  },
  {
    "name": "康-克尼普尔",
    "team": "黄蜂",
    "gp": 81,
    "mpg": 31.5,
    "得分": 18.5,
    "命中-出手": [
      6.4,
      13.4
    ],
    "命中率": 47.5,
    "命中-三分": [
      3.4,
      7.9
    ],
    "三分命中率": 42.5,
    "命中-罚球": [
      2.4,
      2.8
    ],
    "罚球命中率": 86.3,
    "上场时间": 31.5,
    "三分命中数": 3.4,
    "三分出手数": 7.9,
    "罚球命中数": 2.4,
    "罚球出手数": 2.8,
    "pts": 18.5,
    "fgm": 6.4,
    "fga": 13.4,
    "fg_pct": 47.5,
    "tpm": 3.4,
    "tpa": 7.9,
    "tp_pct": 42.5,
    "ftm": 2.4,
    "fta": 2.8,
    "ft_pct": 86.3,
    "ast": 0.0,
    "reb": 0.0,
    "oreb": 0.0,
    "dreb": 0.0,
    "stl": 0.0,
    "blk": 0.0
  },
  {
    "name": "德马尔-德罗赞",
    "team": "国王",
    "gp": 77,
    "mpg": 31.2,
    "得分": 18.4,
    "命中-出手": [
      6.5,
      13.1
    ],
    "命中率": 49.7,
    "命中-三分": [
      0.6,
      1.9
    ],
    "三分命中率": 32.0,
    "命中-罚球": [
      4.9,
      5.6
    ],
    "罚球命中率": 86.8,
    "上场时间": 31.2,
    "助攻数": 4.1,
    "失误数": 1.25,
    "助攻/失误": 3.28,
    "投篮命中率": 49.7,
    "调整命中率": 52.0,
    "命中-投篮": [
      6.5,
      13.1
    ],
    "罚球命中数": 4.9,
    "罚球出手数": 5.6,
    "pts": 18.4,
    "fgm": 6.5,
    "fga": 13.1,
    "fg_pct": 49.7,
    "tpm": 0.6,
    "tpa": 1.9,
    "tp_pct": 32.0,
    "ftm": 4.9,
    "fta": 5.6,
    "ft_pct": 86.8,
    "ast": 0.0,
    "reb": 0.0,
    "oreb": 0.0,
    "dreb": 0.0,
    "stl": 0.0,
    "blk": 0.0
  },
  {
    "name": "阿门·汤普森",
    "team": "火箭",
    "gp": 79,
    "mpg": 37.4,
    "得分": 18.3,
    "命中-出手": [
      7.0,
      13.2
    ],
    "命中率": 53.4,
    "命中-三分": [
      0.3,
      1.5
    ],
    "三分命中率": 21.6,
    "命中-罚球": [
      3.8,
      4.9
    ],
    "罚球命中率": 77.9,
    "上场时间": 37.4,
    "助攻数": 5.3,
    "失误数": 2.41,
    "助攻/失误": 2.2,
    "篮板数": 7.8,
    "进攻篮板": 3.0,
    "防守篮板": 4.8,
    "抢断数": 1.51,
    "犯规数": 2.22,
    "抢断/失误": 0.01,
    "抢断/犯规": 0.68,
    "投篮命中率": 53.4,
    "调整命中率": 54.5,
    "命中-投篮": [
      7.0,
      13.2
    ],
    "pts": 18.3,
    "fgm": 7.0,
    "fga": 13.2,
    "fg_pct": 53.4,
    "tpm": 0.3,
    "tpa": 1.5,
    "tp_pct": 21.6,
    "ftm": 3.8,
    "fta": 4.9,
    "ft_pct": 77.9,
    "ast": 0.0,
    "reb": 0.0,
    "oreb": 0.0,
    "dreb": 0.0,
    "stl": 0.0,
    "blk": 0.0
  },
  {
    "name": "埃文-莫布利",
    "team": "骑士",
    "gp": 65,
    "mpg": 31.9,
    "得分": 18.2,
    "命中-出手": [
      7.2,
      13.2
    ],
    "命中率": 54.6,
    "命中-三分": [
      0.9,
      3.2
    ],
    "三分命中率": 29.7,
    "命中-罚球": [
      2.8,
      4.6
    ],
    "罚球命中率": 60.6,
    "上场时间": 31.9,
    "篮板数": 9.0,
    "进攻篮板": 2.4,
    "防守篮板": 6.6,
    "盖帽数": 1.74,
    "犯规数": 2.45,
    "盖帽/犯规": 0.71,
    "投篮命中率": 54.6,
    "调整命中率": 58.2,
    "命中-投篮": [
      7.2,
      13.2
    ],
    "pts": 18.2,
    "fgm": 7.2,
    "fga": 13.2,
    "fg_pct": 54.6,
    "tpm": 0.9,
    "tpa": 3.2,
    "tp_pct": 29.7,
    "ftm": 2.8,
    "fta": 4.6,
    "ft_pct": 60.6,
    "ast": 0.0,
    "reb": 0.0,
    "oreb": 0.0,
    "dreb": 0.0,
    "stl": 0.0,
    "blk": 0.0
  },
  {
    "name": "斯科蒂-巴恩斯",
    "team": "猛龙",
    "gp": 80,
    "mpg": 33.5,
    "得分": 18.1,
    "命中-出手": [
      7.1,
      14.0
    ],
    "命中率": 50.7,
    "命中-三分": [
      0.9,
      2.8
    ],
    "三分命中率": 30.4,
    "命中-罚球": [
      3.0,
      3.7
    ],
    "罚球命中率": 81.5,
    "上场时间": 33.5,
    "助攻数": 5.9,
    "失误数": 2.63,
    "助攻/失误": 2.24,
    "篮板数": 7.5,
    "进攻篮板": 1.9,
    "防守篮板": 5.6,
    "抢断数": 1.43,
    "犯规数": 2.64,
    "抢断/失误": 0.01,
    "抢断/犯规": 0.54,
    "盖帽数": 1.45,
    "盖帽/犯规": 0.55,
    "投篮命中率": 50.7,
    "调整命中率": 53.7,
    "命中-投篮": [
      7.1,
      14.0
    ],
    "pts": 18.1,
    "fgm": 7.1,
    "fga": 14.0,
    "fg_pct": 50.7,
    "tpm": 0.9,
    "tpa": 2.8,
    "tp_pct": 30.4,
    "ftm": 3.0,
    "fta": 3.7,
    "ft_pct": 81.5,
    "ast": 0.0,
    "reb": 0.0,
    "oreb": 0.0,
    "dreb": 0.0,
    "stl": 0.0,
    "blk": 0.0
  },
  {
    "name": "萨迪克-贝",
    "team": "鹈鹕",
    "gp": 72,
    "mpg": 31.2,
    "得分": 17.7,
    "命中-出手": [
      6.1,
      13.4
    ],
    "命中率": 45.1,
    "命中-三分": [
      2.1,
      5.7
    ],
    "三分命中率": 36.7,
    "命中-罚球": [
      3.4,
      4.1
    ],
    "罚球命中率": 84.1,
    "上场时间": 31.2,
    "罚球命中数": 3.4,
    "罚球出手数": 4.1,
    "pts": 17.7,
    "fgm": 6.1,
    "fga": 13.4,
    "fg_pct": 45.1,
    "tpm": 2.1,
    "tpa": 5.7,
    "tp_pct": 36.7,
    "ftm": 3.4,
    "fta": 4.1,
    "ft_pct": 84.1,
    "ast": 0.0,
    "reb": 0.0,
    "oreb": 0.0,
    "dreb": 0.0,
    "stl": 0.0,
    "blk": 0.0
  },
  {
    "name": "莱恩-罗林斯",
    "team": "雄鹿",
    "gp": 74,
    "mpg": 32.1,
    "得分": 17.3,
    "命中-出手": [
      6.6,
      13.9
    ],
    "命中率": 47.2,
    "命中-三分": [
      2.5,
      6.1
    ],
    "三分命中率": 40.6,
    "命中-罚球": [
      1.7,
      2.1
    ],
    "罚球命中率": 79.6,
    "上场时间": 32.1,
    "助攻数": 5.6,
    "失误数": 2.72,
    "助攻/失误": 2.06,
    "抢断数": 1.49,
    "犯规数": 2.61,
    "抢断/失误": 0.01,
    "抢断/犯规": 0.57,
    "三分命中数": 2.5,
    "三分出手数": 6.1,
    "pts": 17.3,
    "fgm": 6.6,
    "fga": 13.9,
    "fg_pct": 47.2,
    "tpm": 2.5,
    "tpa": 6.1,
    "tp_pct": 40.6,
    "ftm": 1.7,
    "fta": 2.1,
    "ft_pct": 79.6,
    "ast": 0.0,
    "reb": 0.0,
    "oreb": 0.0,
    "dreb": 0.0,
    "stl": 0.0,
    "blk": 0.0
  },
  {
    "name": "迈尔斯-布里奇斯",
    "team": "黄蜂",
    "gp": 77,
    "mpg": 31.0,
    "得分": 17.1,
    "命中-出手": [
      6.2,
      13.5
    ],
    "命中率": 46.0,
    "命中-三分": [
      1.9,
      5.8
    ],
    "三分命中率": 33.3,
    "命中-罚球": [
      2.7,
      3.3
    ],
    "罚球命中率": 82.2,
    "上场时间": 31.0,
    "篮板数": 5.8,
    "进攻篮板": 1.0,
    "防守篮板": 4.9,
    "罚球命中数": 2.7,
    "罚球出手数": 3.3,
    "pts": 17.1,
    "fgm": 6.2,
    "fga": 13.5,
    "fg_pct": 46.0,
    "tpm": 1.9,
    "tpa": 5.8,
    "tp_pct": 33.3,
    "ftm": 2.7,
    "fta": 3.3,
    "ft_pct": 82.2,
    "ast": 0.0,
    "reb": 0.0,
    "oreb": 0.0,
    "dreb": 0.0,
    "stl": 0.0,
    "blk": 0.0
  },
  {
    "name": "切特-霍姆格伦",
    "team": "雷霆",
    "gp": 69,
    "mpg": 28.9,
    "得分": 17.1,
    "命中-出手": [
      6.3,
      11.3
    ],
    "命中率": 55.7,
    "命中-三分": [
      1.3,
      3.5
    ],
    "三分命中率": 36.2,
    "命中-罚球": [
      3.3,
      4.1
    ],
    "罚球命中率": 79.2,
    "上场时间": 28.9,
    "篮板数": 8.9,
    "进攻篮板": 1.9,
    "防守篮板": 7.0,
    "盖帽数": 1.9,
    "犯规数": 2.29,
    "盖帽/犯规": 0.83,
    "投篮命中率": 55.7,
    "调整命中率": 61.4,
    "命中-投篮": [
      6.3,
      11.3
    ],
    "pts": 17.1,
    "fgm": 6.3,
    "fga": 11.3,
    "fg_pct": 55.7,
    "tpm": 1.3,
    "tpa": 3.5,
    "tp_pct": 36.2,
    "ftm": 3.3,
    "fta": 4.1,
    "ft_pct": 79.2,
    "ast": 0.0,
    "reb": 0.0,
    "oreb": 0.0,
    "dreb": 0.0,
    "stl": 0.0,
    "blk": 0.0
  },
  {
    "name": "佩顿-普里查德",
    "team": "凯尔特人",
    "gp": 79,
    "mpg": 32.4,
    "得分": 17.0,
    "命中-出手": [
      6.4,
      13.8
    ],
    "命中率": 46.4,
    "命中-三分": [
      2.7,
      7.1
    ],
    "三分命中率": 37.7,
    "命中-罚球": [
      1.5,
      1.7
    ],
    "罚球命中率": 89.0,
    "上场时间": 32.4,
    "助攻数": 5.2,
    "失误数": 1.38,
    "助攻/失误": 3.77,
    "pts": 17.0,
    "fgm": 6.4,
    "fga": 13.8,
    "fg_pct": 46.4,
    "tpm": 2.7,
    "tpa": 7.1,
    "tp_pct": 37.7,
    "ftm": 1.5,
    "fta": 1.7,
    "ft_pct": 89.0,
    "ast": 0.0,
    "reb": 0.0,
    "oreb": 0.0,
    "dreb": 0.0,
    "stl": 0.0,
    "blk": 0.0
  },
  {
    "name": "OG-阿奴诺比",
    "team": "尼克斯",
    "gp": 67,
    "mpg": 33.2,
    "得分": 16.7,
    "命中-出手": [
      5.8,
      12.0
    ],
    "命中率": 48.4,
    "命中-三分": [
      2.3,
      6.1
    ],
    "三分命中率": 38.6,
    "命中-罚球": [
      2.7,
      3.3
    ],
    "罚球命中率": 82.8,
    "上场时间": 33.2,
    "抢断数": 1.55,
    "失误数": 1.84,
    "犯规数": 2.45,
    "抢断/失误": 0.01,
    "抢断/犯规": 0.63,
    "盖帽数": 0.72,
    "盖帽/犯规": 0.29,
    "三分命中数": 2.3,
    "三分出手数": 6.1,
    "罚球命中数": 2.7,
    "罚球出手数": 3.3,
    "pts": 16.7,
    "fgm": 5.8,
    "fga": 12.0,
    "fg_pct": 48.4,
    "tpm": 2.3,
    "tpa": 6.1,
    "tp_pct": 38.6,
    "ftm": 2.7,
    "fta": 3.3,
    "ft_pct": 82.8,
    "ast": 0.0,
    "reb": 0.0,
    "oreb": 0.0,
    "dreb": 0.0,
    "stl": 0.0,
    "blk": 0.0
  },
  {
    "name": "斯蒂芬·卡斯尔",
    "team": "马刺",
    "gp": 68,
    "mpg": 30.0,
    "得分": 16.7,
    "命中-出手": [
      5.7,
      12.0
    ],
    "命中率": 47.1,
    "命中-三分": [
      1.2,
      3.6
    ],
    "三分命中率": 33.2,
    "命中-罚球": [
      4.2,
      5.7
    ],
    "罚球命中率": 73.4,
    "上场时间": 30.0,
    "助攻数": 7.4,
    "失误数": 3.19,
    "助攻/失误": 2.32,
    "抢断数": 1.15,
    "犯规数": 3.26,
    "抢断/失误": 0.01,
    "抢断/犯规": 0.35,
    "pts": 16.7,
    "fgm": 5.7,
    "fga": 12.0,
    "fg_pct": 47.1,
    "tpm": 1.2,
    "tpa": 3.6,
    "tp_pct": 33.2,
    "ftm": 4.2,
    "fta": 5.7,
    "ft_pct": 73.4,
    "ast": 0.0,
    "reb": 0.0,
    "oreb": 0.0,
    "dreb": 0.0,
    "stl": 0.0,
    "blk": 0.0
  },
  {
    "name": "德里克-怀特",
    "team": "凯尔特人",
    "gp": 77,
    "mpg": 34.1,
    "得分": 16.5,
    "命中-出手": [
      5.7,
      14.4
    ],
    "命中率": 39.4,
    "命中-三分": [
      2.7,
      8.3
    ],
    "三分命中率": 32.7,
    "命中-罚球": [
      2.4,
      2.7
    ],
    "罚球命中率": 90.2,
    "上场时间": 34.1,
    "助攻数": 5.4,
    "失误数": 1.74,
    "助攻/失误": 3.1,
    "抢断数": 1.14,
    "犯规数": 1.55,
    "抢断/失误": 0.01,
    "抢断/犯规": 0.74,
    "盖帽数": 1.27,
    "盖帽/犯规": 0.82,
    "罚球命中数": 2.4,
    "罚球出手数": 2.7,
    "pts": 16.5,
    "fgm": 5.7,
    "fga": 14.4,
    "fg_pct": 39.4,
    "tpm": 2.7,
    "tpa": 8.3,
    "tp_pct": 32.7,
    "ftm": 2.4,
    "fta": 2.7,
    "ft_pct": 90.2,
    "ast": 0.0,
    "reb": 0.0,
    "oreb": 0.0,
    "dreb": 0.0,
    "stl": 0.0,
    "blk": 0.0
  },
  {
    "name": "伊曼纽尔-奎克利",
    "team": "猛龙",
    "gp": 70,
    "mpg": 31.9,
    "得分": 16.4,
    "命中-出手": [
      5.7,
      12.9
    ],
    "命中率": 44.3,
    "命中-三分": [
      2.5,
      6.8
    ],
    "三分命中率": 37.4,
    "命中-罚球": [
      2.4,
      3.0
    ],
    "罚球命中率": 82.1,
    "上场时间": 31.9,
    "助攻数": 5.9,
    "失误数": 1.46,
    "助攻/失误": 4.04,
    "抢断数": 1.31,
    "犯规数": 2.01,
    "抢断/失误": 0.01,
    "抢断/犯规": 0.65,
    "罚球命中数": 2.4,
    "罚球出手数": 3.0,
    "pts": 16.4,
    "fgm": 5.7,
    "fga": 12.9,
    "fg_pct": 44.3,
    "tpm": 2.5,
    "tpa": 6.8,
    "tp_pct": 37.4,
    "ftm": 2.4,
    "fta": 3.0,
    "ft_pct": 82.1,
    "ast": 0.0,
    "reb": 0.0,
    "oreb": 0.0,
    "dreb": 0.0,
    "stl": 0.0,
    "blk": 0.0
  },
  {
    "name": "马塔斯·布泽利斯",
    "team": "公牛",
    "gp": 77,
    "mpg": 29.2,
    "得分": 16.3,
    "命中-出手": [
      5.8,
      12.5
    ],
    "命中率": 46.3,
    "命中-三分": [
      2.2,
      6.4
    ],
    "三分命中率": 34.9,
    "命中-罚球": [
      2.4,
      3.1
    ],
    "罚球命中率": 78.6,
    "上场时间": 29.2,
    "篮板数": 5.8,
    "进攻篮板": 1.0,
    "防守篮板": 4.8,
    "盖帽数": 1.51,
    "犯规数": 2.3,
    "盖帽/犯规": 0.66,
    "pts": 16.3,
    "fgm": 5.8,
    "fga": 12.5,
    "fg_pct": 46.3,
    "tpm": 2.2,
    "tpa": 6.4,
    "tp_pct": 34.9,
    "ftm": 2.4,
    "fta": 3.1,
    "ft_pct": 78.6,
    "ast": 0.0,
    "reb": 0.0,
    "oreb": 0.0,
    "dreb": 0.0,
    "stl": 0.0,
    "blk": 0.0
  },
  {
    "name": "VJ-埃奇库姆",
    "team": "76人",
    "gp": 75,
    "mpg": 35.0,
    "得分": 16.0,
    "命中-出手": [
      6.0,
      13.7
    ],
    "命中率": 43.8,
    "命中-三分": [
      2.0,
      5.6
    ],
    "三分命中率": 35.4,
    "命中-罚球": [
      2.0,
      2.4
    ],
    "罚球命中率": 81.8,
    "上场时间": 35.0,
    "助攻数": 4.2,
    "失误数": 1.83,
    "助攻/失误": 2.3,
    "抢断数": 1.43,
    "犯规数": 2.85,
    "抢断/失误": 0.01,
    "抢断/犯规": 0.5,
    "罚球命中数": 2.0,
    "罚球出手数": 2.4,
    "pts": 16.0,
    "fgm": 6.0,
    "fga": 13.7,
    "fg_pct": 43.8,
    "tpm": 2.0,
    "tpa": 5.6,
    "tp_pct": 35.4,
    "ftm": 2.0,
    "fta": 2.4,
    "ft_pct": 81.8,
    "ast": 0.0,
    "reb": 0.0,
    "oreb": 0.0,
    "dreb": 0.0,
    "stl": 0.0,
    "blk": 0.0
  },
  {
    "name": "纳兹-里德",
    "team": "森林狼",
    "gp": 77,
    "mpg": 26.1,
    "篮板数": 6.2,
    "进攻篮板": 1.2,
    "防守篮板": 5.0,
    "上场时间": 26.1,
    "盖帽数": 1.01,
    "犯规数": 2.53,
    "盖帽/犯规": 0.4,
    "pts": 0.0,
    "fgm": 0,
    "fga": 0,
    "fg_pct": 0.0,
    "tpm": 0,
    "tpa": 0,
    "tp_pct": 0.0,
    "ftm": 0,
    "fta": 0,
    "ft_pct": 0.0,
    "ast": 0.0,
    "reb": 0.0,
    "oreb": 0.0,
    "dreb": 0.0,
    "stl": 0.0,
    "blk": 0.0
  },
  {
    "name": "哈里森-巴恩斯",
    "team": "马刺",
    "gp": 77,
    "mpg": 25.8,
    "三分命中率": 38.8,
    "三分命中数": 1.8,
    "三分出手数": 4.7,
    "得分": 9.9,
    "上场时间": 25.8,
    "pts": 0.0,
    "fgm": 0,
    "fga": 0,
    "fg_pct": 0.0,
    "tpm": 0,
    "tpa": 0,
    "tp_pct": 0.0,
    "ftm": 0,
    "fta": 0,
    "ft_pct": 0.0,
    "ast": 0.0,
    "reb": 0.0,
    "oreb": 0.0,
    "dreb": 0.0,
    "stl": 0.0,
    "blk": 0.0
  },
  {
    "name": "杰拉米-格兰特",
    "team": "开拓者",
    "gp": 57,
    "mpg": 29.7,
    "三分命中率": 38.9,
    "三分命中数": 2.4,
    "三分出手数": 6.1,
    "得分": 18.6,
    "上场时间": 29.7,
    "pts": 0.0,
    "fgm": 0,
    "fga": 0,
    "fg_pct": 0.0,
    "tpm": 0,
    "tpa": 0,
    "tp_pct": 0.0,
    "ftm": 0,
    "fta": 0,
    "ft_pct": 0.0,
    "ast": 0.0,
    "reb": 0.0,
    "oreb": 0.0,
    "dreb": 0.0,
    "stl": 0.0,
    "blk": 0.0
  },
  {
    "name": "格雷森-阿伦",
    "team": "太阳",
    "gp": 51,
    "mpg": 28.8,
    "罚球命中率": 85.7,
    "罚球命中数": 2.8,
    "罚球出手数": 3.3,
    "得分": 16.5,
    "上场时间": 28.8,
    "pts": 0.0,
    "fgm": 0,
    "fga": 0,
    "fg_pct": 0.0,
    "tpm": 0,
    "tpa": 0,
    "tp_pct": 0.0,
    "ftm": 0,
    "fta": 0,
    "ft_pct": 0.0,
    "ast": 0.0,
    "reb": 0.0,
    "oreb": 0.0,
    "dreb": 0.0,
    "stl": 0.0,
    "blk": 0.0
  },
  {
    "name": "纳吉-马绍尔",
    "team": "独行侠",
    "gp": 74,
    "mpg": 29.5,
    "投篮命中率": 51.0,
    "调整命中率": 54.8,
    "命中-投篮": [
      5.7,
      11.1
    ],
    "命中-三分": [
      0.8,
      2.9
    ],
    "上场时间": 29.5,
    "pts": 0.0,
    "fgm": 0,
    "fga": 0,
    "fg_pct": 0.0,
    "tpm": 0,
    "tpa": 0,
    "tp_pct": 0.0,
    "ftm": 0,
    "fta": 0,
    "ft_pct": 0.0,
    "ast": 0.0,
    "reb": 0.0,
    "oreb": 0.0,
    "dreb": 0.0,
    "stl": 0.0,
    "blk": 0.0
  },
  {
    "name": "凯莱尔·韦尔",
    "team": "热火",
    "gp": 77,
    "mpg": 22.1,
    "篮板数": 9.0,
    "进攻篮板": 2.8,
    "防守篮板": 6.2,
    "上场时间": 22.1,
    "盖帽数": 1.09,
    "犯规数": 1.55,
    "盖帽/犯规": 0.7,
    "投篮命中率": 53.0,
    "调整命中率": 60.1,
    "命中-投篮": [
      4.5,
      8.4
    ],
    "命中-三分": [
      1.2,
      3.0
    ],
    "三分命中率": 39.5,
    "三分命中数": 1.2,
    "三分出手数": 3.0,
    "得分": 11.1,
    "pts": 0.0,
    "fgm": 0,
    "fga": 0,
    "fg_pct": 0.0,
    "tpm": 0,
    "tpa": 0,
    "tp_pct": 0.0,
    "ftm": 0,
    "fta": 0,
    "ft_pct": 0.0,
    "ast": 0.0,
    "reb": 0.0,
    "oreb": 0.0,
    "dreb": 0.0,
    "stl": 0.0,
    "blk": 0.0
  },
  {
    "name": "凯尔-库兹马",
    "team": "雄鹿",
    "gp": 69,
    "mpg": 26.2,
    "投篮命中率": 49.2,
    "调整命中率": 55.2,
    "命中-投篮": [
      4.9,
      10.0
    ],
    "命中-三分": [
      1.2,
      3.5
    ],
    "上场时间": 26.2,
    "pts": 0.0,
    "fgm": 0,
    "fga": 0,
    "fg_pct": 0.0,
    "tpm": 0,
    "tpa": 0,
    "tp_pct": 0.0,
    "ftm": 0,
    "fta": 0,
    "ft_pct": 0.0,
    "ast": 0.0,
    "reb": 0.0,
    "oreb": 0.0,
    "dreb": 0.0,
    "stl": 0.0,
    "blk": 0.0
  },
  {
    "name": "纳肖恩-海兰德",
    "team": "森林狼",
    "gp": 71,
    "mpg": 16.6,
    "三分命中率": 38.8,
    "三分命中数": 1.6,
    "三分出手数": 4.2,
    "得分": 8.5,
    "上场时间": 16.6,
    "pts": 0.0,
    "fgm": 0,
    "fga": 0,
    "fg_pct": 0.0,
    "tpm": 0,
    "tpa": 0,
    "tp_pct": 0.0,
    "ftm": 0,
    "fta": 0,
    "ft_pct": 0.0,
    "ast": 0.0,
    "reb": 0.0,
    "oreb": 0.0,
    "dreb": 0.0,
    "stl": 0.0,
    "blk": 0.0
  },
  {
    "name": "狄龙-布鲁克斯",
    "team": "太阳",
    "gp": 56,
    "mpg": 30.4,
    "罚球命中率": 84.2,
    "罚球命中数": 3.0,
    "罚球出手数": 3.6,
    "得分": 20.2,
    "上场时间": 30.4,
    "pts": 0.0,
    "fgm": 0,
    "fga": 0,
    "fg_pct": 0.0,
    "tpm": 0,
    "tpa": 0,
    "tp_pct": 0.0,
    "ftm": 0,
    "fta": 0,
    "ft_pct": 0.0,
    "ast": 0.0,
    "reb": 0.0,
    "oreb": 0.0,
    "dreb": 0.0,
    "stl": 0.0,
    "blk": 0.0
  },
  {
    "name": "斯维亚托斯拉夫-米哈伊柳克",
    "team": "爵士",
    "gp": 50,
    "mpg": 23.1,
    "三分命中率": 40.8,
    "三分命中数": 2.0,
    "三分出手数": 4.8,
    "得分": 9.4,
    "上场时间": 23.1,
    "pts": 0.0,
    "fgm": 0,
    "fga": 0,
    "fg_pct": 0.0,
    "tpm": 0,
    "tpa": 0,
    "tp_pct": 0.0,
    "ftm": 0,
    "fta": 0,
    "ft_pct": 0.0,
    "ast": 0.0,
    "reb": 0.0,
    "oreb": 0.0,
    "dreb": 0.0,
    "stl": 0.0,
    "blk": 0.0
  },
  {
    "name": "乔丹-古德温",
    "team": "太阳",
    "gp": 70,
    "mpg": 22.5,
    "抢断数": 1.51,
    "失误数": 0.97,
    "犯规数": 1.9,
    "抢断/失误": 0.02,
    "抢断/犯规": 0.79,
    "上场时间": 22.5,
    "pts": 0.0,
    "fgm": 0,
    "fga": 0,
    "fg_pct": 0.0,
    "tpm": 0,
    "tpa": 0,
    "tp_pct": 0.0,
    "ftm": 0,
    "fta": 0,
    "ft_pct": 0.0,
    "ast": 0.0,
    "reb": 0.0,
    "oreb": 0.0,
    "dreb": 0.0,
    "stl": 0.0,
    "blk": 0.0
  },
  {
    "name": "卡尔顿·卡林顿",
    "team": "奇才",
    "gp": 82,
    "mpg": 27.7,
    "助攻数": 4.6,
    "失误数": 2.33,
    "助攻/失误": 1.97,
    "上场时间": 27.7,
    "三分命中率": 40.8,
    "三分命中数": 2.1,
    "三分出手数": 5.1,
    "得分": 10.7,
    "pts": 0.0,
    "fgm": 0,
    "fga": 0,
    "fg_pct": 0.0,
    "tpm": 0,
    "tpa": 0,
    "tp_pct": 0.0,
    "ftm": 0,
    "fta": 0,
    "ft_pct": 0.0,
    "ast": 0.0,
    "reb": 0.0,
    "oreb": 0.0,
    "dreb": 0.0,
    "stl": 0.0,
    "blk": 0.0
  },
  {
    "name": "杰克-拉拉维亚",
    "team": "湖人",
    "gp": 82,
    "mpg": 25.1,
    "抢断数": 1.27,
    "失误数": 1.06,
    "犯规数": 2.39,
    "抢断/失误": 0.01,
    "抢断/犯规": 0.53,
    "上场时间": 25.1,
    "pts": 0.0,
    "fgm": 0,
    "fga": 0,
    "fg_pct": 0.0,
    "tpm": 0,
    "tpa": 0,
    "tp_pct": 0.0,
    "ftm": 0,
    "fta": 0,
    "ft_pct": 0.0,
    "ast": 0.0,
    "reb": 0.0,
    "oreb": 0.0,
    "dreb": 0.0,
    "stl": 0.0,
    "blk": 0.0
  },
  {
    "name": "保罗-乔治",
    "team": "76人",
    "gp": 37,
    "mpg": 30.7,
    "三分命中率": 39.2,
    "三分命中数": 2.7,
    "三分出手数": 6.9,
    "得分": 17.3,
    "上场时间": 30.7,
    "pts": 0.0,
    "fgm": 0,
    "fga": 0,
    "fg_pct": 0.0,
    "tpm": 0,
    "tpa": 0,
    "tp_pct": 0.0,
    "ftm": 0,
    "fta": 0,
    "ft_pct": 0.0,
    "ast": 0.0,
    "reb": 0.0,
    "oreb": 0.0,
    "dreb": 0.0,
    "stl": 0.0,
    "blk": 0.0
  },
  {
    "name": "德鲁-史密斯",
    "team": "热火",
    "gp": 70,
    "mpg": 16.3,
    "抢断数": 1.43,
    "失误数": 0.79,
    "犯规数": 1.56,
    "抢断/失误": 0.03,
    "抢断/犯规": 0.92,
    "上场时间": 16.3,
    "pts": 0.0,
    "fgm": 0,
    "fga": 0,
    "fg_pct": 0.0,
    "tpm": 0,
    "tpa": 0,
    "tp_pct": 0.0,
    "ftm": 0,
    "fta": 0,
    "ft_pct": 0.0,
    "ast": 0.0,
    "reb": 0.0,
    "oreb": 0.0,
    "dreb": 0.0,
    "stl": 0.0,
    "blk": 0.0
  },
  {
    "name": "贾科比·沃尔特",
    "team": "猛龙",
    "gp": 72,
    "mpg": 20.5,
    "三分命中率": 40.9,
    "三分命中数": 1.5,
    "三分出手数": 3.7,
    "得分": 7.5,
    "上场时间": 20.5,
    "pts": 0.0,
    "fgm": 0,
    "fga": 0,
    "fg_pct": 0.0,
    "tpm": 0,
    "tpa": 0,
    "tp_pct": 0.0,
    "ftm": 0,
    "fta": 0,
    "ft_pct": 0.0,
    "ast": 0.0,
    "reb": 0.0,
    "oreb": 0.0,
    "dreb": 0.0,
    "stl": 0.0,
    "blk": 0.0
  },
  {
    "name": "博比-波蒂斯",
    "team": "雄鹿",
    "gp": 67,
    "mpg": 24.2,
    "篮板数": 6.4,
    "进攻篮板": 1.3,
    "防守篮板": 5.1,
    "上场时间": 24.2,
    "投篮命中率": 48.8,
    "调整命中率": 57.8,
    "命中-投篮": [
      5.5,
      11.2
    ],
    "命中-三分": [
      2.0,
      4.4
    ],
    "三分命中率": 45.6,
    "三分命中数": 2.0,
    "三分出手数": 4.4,
    "得分": 13.7,
    "pts": 0.0,
    "fgm": 0,
    "fga": 0,
    "fg_pct": 0.0,
    "tpm": 0,
    "tpa": 0,
    "tp_pct": 0.0,
    "ftm": 0,
    "fta": 0,
    "ft_pct": 0.0,
    "ast": 0.0,
    "reb": 0.0,
    "oreb": 0.0,
    "dreb": 0.0,
    "stl": 0.0,
    "blk": 0.0
  },
  {
    "name": "克里斯-邓恩",
    "team": "快船",
    "gp": 82,
    "mpg": 27.2,
    "抢断数": 1.6,
    "失误数": 1.35,
    "犯规数": 2.3,
    "抢断/失误": 0.01,
    "抢断/犯规": 0.7,
    "上场时间": 27.2,
    "pts": 0.0,
    "fgm": 0,
    "fga": 0,
    "fg_pct": 0.0,
    "tpm": 0,
    "tpa": 0,
    "tp_pct": 0.0,
    "ftm": 0,
    "fta": 0,
    "ft_pct": 0.0,
    "ast": 0.0,
    "reb": 0.0,
    "oreb": 0.0,
    "dreb": 0.0,
    "stl": 0.0,
    "blk": 0.0
  },
  {
    "name": "卡梅隆·斯宾塞",
    "team": "灰熊",
    "gp": 72,
    "mpg": 23.8,
    "助攻数": 5.6,
    "失误数": 1.29,
    "助攻/失误": 4.34,
    "上场时间": 23.8,
    "三分命中率": 44.9,
    "三分命中数": 2.0,
    "三分出手数": 4.5,
    "得分": 11.1,
    "罚球命中率": 94.0,
    "罚球命中数": 1.8,
    "罚球出手数": 1.9,
    "pts": 0.0,
    "fgm": 0,
    "fga": 0,
    "fg_pct": 0.0,
    "tpm": 0,
    "tpa": 0,
    "tp_pct": 0.0,
    "ftm": 0,
    "fta": 0,
    "ft_pct": 0.0,
    "ast": 0.0,
    "reb": 0.0,
    "oreb": 0.0,
    "dreb": 0.0,
    "stl": 0.0,
    "blk": 0.0
  },
  {
    "name": "瑞安-卡尔克布伦纳",
    "team": "黄蜂",
    "gp": 69,
    "mpg": 21.4,
    "盖帽数": 1.46,
    "犯规数": 1.55,
    "盖帽/犯规": 0.94,
    "上场时间": 21.4,
    "pts": 0.0,
    "fgm": 0,
    "fga": 0,
    "fg_pct": 0.0,
    "tpm": 0,
    "tpa": 0,
    "tp_pct": 0.0,
    "ftm": 0,
    "fta": 0,
    "ft_pct": 0.0,
    "ast": 0.0,
    "reb": 0.0,
    "oreb": 0.0,
    "dreb": 0.0,
    "stl": 0.0,
    "blk": 0.0
  },
  {
    "name": "贾勒特-阿伦",
    "team": "骑士",
    "gp": 56,
    "mpg": 27.1,
    "投篮命中率": 63.8,
    "调整命中率": 63.9,
    "命中-投篮": [
      6.0,
      9.4
    ],
    "命中-三分": [
      0.0,
      0.2
    ],
    "上场时间": 27.1,
    "pts": 0.0,
    "fgm": 0,
    "fga": 0,
    "fg_pct": 0.0,
    "tpm": 0,
    "tpa": 0,
    "tp_pct": 0.0,
    "ftm": 0,
    "fta": 0,
    "ft_pct": 0.0,
    "ast": 0.0,
    "reb": 0.0,
    "oreb": 0.0,
    "dreb": 0.0,
    "stl": 0.0,
    "blk": 0.0
  },
  {
    "name": "马克斯-克里斯蒂",
    "team": "独行侠",
    "gp": 77,
    "mpg": 29.1,
    "三分命中率": 40.4,
    "三分命中数": 2.3,
    "三分出手数": 5.8,
    "得分": 12.3,
    "上场时间": 29.1,
    "罚球命中率": 89.9,
    "罚球命中数": 1.6,
    "罚球出手数": 1.8,
    "pts": 0.0,
    "fgm": 0,
    "fga": 0,
    "fg_pct": 0.0,
    "tpm": 0,
    "tpa": 0,
    "tp_pct": 0.0,
    "ftm": 0,
    "fta": 0,
    "ft_pct": 0.0,
    "ast": 0.0,
    "reb": 0.0,
    "oreb": 0.0,
    "dreb": 0.0,
    "stl": 0.0,
    "blk": 0.0
  },
  {
    "name": "瑞安-内姆布哈德",
    "team": "独行侠",
    "gp": 60,
    "mpg": 19.5,
    "助攻数": 5.3,
    "失误数": 1.42,
    "助攻/失误": 3.73,
    "上场时间": 19.5,
    "pts": 0.0,
    "fgm": 0,
    "fga": 0,
    "fg_pct": 0.0,
    "tpm": 0,
    "tpa": 0,
    "tp_pct": 0.0,
    "ftm": 0,
    "fta": 0,
    "ft_pct": 0.0,
    "ast": 0.0,
    "reb": 0.0,
    "oreb": 0.0,
    "dreb": 0.0,
    "stl": 0.0,
    "blk": 0.0
  },
  {
    "name": "朱利安-尚彭尼",
    "team": "马刺",
    "gp": 82,
    "mpg": 27.6,
    "篮板数": 5.8,
    "进攻篮板": 0.9,
    "防守篮板": 4.9,
    "上场时间": 27.6,
    "pts": 0.0,
    "fgm": 0,
    "fga": 0,
    "fg_pct": 0.0,
    "tpm": 0,
    "tpa": 0,
    "tp_pct": 0.0,
    "ftm": 0,
    "fta": 0,
    "ft_pct": 0.0,
    "ast": 0.0,
    "reb": 0.0,
    "oreb": 0.0,
    "dreb": 0.0,
    "stl": 0.0,
    "blk": 0.0
  },
  {
    "name": "拉塞尔-威斯布鲁克",
    "team": "国王",
    "gp": 64,
    "mpg": 29.0,
    "助攻数": 6.7,
    "失误数": 3.27,
    "助攻/失误": 2.05,
    "上场时间": 29.0,
    "抢断数": 1.3,
    "犯规数": 2.3,
    "抢断/失误": 0.01,
    "抢断/犯规": 0.57,
    "pts": 0.0,
    "fgm": 0,
    "fga": 0,
    "fg_pct": 0.0,
    "tpm": 0,
    "tpa": 0,
    "tp_pct": 0.0,
    "ftm": 0,
    "fta": 0,
    "ft_pct": 0.0,
    "ast": 0.0,
    "reb": 0.0,
    "oreb": 0.0,
    "dreb": 0.0,
    "stl": 0.0,
    "blk": 0.0
  },
  {
    "name": "马克-威廉姆斯",
    "team": "太阳",
    "gp": 60,
    "mpg": 23.6,
    "篮板数": 7.9,
    "进攻篮板": 3.1,
    "防守篮板": 4.9,
    "上场时间": 23.6,
    "盖帽数": 0.92,
    "犯规数": 2.2,
    "盖帽/犯规": 0.42,
    "pts": 0.0,
    "fgm": 0,
    "fga": 0,
    "fg_pct": 0.0,
    "tpm": 0,
    "tpa": 0,
    "tp_pct": 0.0,
    "ftm": 0,
    "fta": 0,
    "ft_pct": 0.0,
    "ast": 0.0,
    "reb": 0.0,
    "oreb": 0.0,
    "dreb": 0.0,
    "stl": 0.0,
    "blk": 0.0
  },
  {
    "name": "温德尔-卡特",
    "team": "魔术",
    "gp": 78,
    "mpg": 29.3,
    "篮板数": 7.4,
    "进攻篮板": 2.1,
    "防守篮板": 5.3,
    "上场时间": 29.3,
    "投篮命中率": 51.2,
    "调整命中率": 56.8,
    "命中-投篮": [
      4.2,
      8.2
    ],
    "命中-三分": [
      0.9,
      2.9
    ],
    "pts": 0.0,
    "fgm": 0,
    "fga": 0,
    "fg_pct": 0.0,
    "tpm": 0,
    "tpa": 0,
    "tp_pct": 0.0,
    "ftm": 0,
    "fta": 0,
    "ft_pct": 0.0,
    "ast": 0.0,
    "reb": 0.0,
    "oreb": 0.0,
    "dreb": 0.0,
    "stl": 0.0,
    "blk": 0.0
  },
  {
    "name": "卢克-科内特",
    "team": "马刺",
    "gp": 68,
    "mpg": 21.0,
    "篮板数": 6.1,
    "进攻篮板": 2.7,
    "防守篮板": 3.4,
    "上场时间": 21.0,
    "盖帽数": 0.96,
    "犯规数": 1.76,
    "盖帽/犯规": 0.55,
    "pts": 0.0,
    "fgm": 0,
    "fga": 0,
    "fg_pct": 0.0,
    "tpm": 0,
    "tpa": 0,
    "tp_pct": 0.0,
    "ftm": 0,
    "fta": 0,
    "ft_pct": 0.0,
    "ast": 0.0,
    "reb": 0.0,
    "oreb": 0.0,
    "dreb": 0.0,
    "stl": 0.0,
    "blk": 0.0
  },
  {
    "name": "罗伯特-威廉姆斯",
    "team": "开拓者",
    "gp": 59,
    "mpg": 17.1,
    "篮板数": 7.0,
    "进攻篮板": 2.4,
    "防守篮板": 4.6,
    "上场时间": 17.1,
    "盖帽数": 1.47,
    "犯规数": 1.25,
    "盖帽/犯规": 1.18,
    "pts": 0.0,
    "fgm": 0,
    "fga": 0,
    "fg_pct": 0.0,
    "tpm": 0,
    "tpa": 0,
    "tp_pct": 0.0,
    "ftm": 0,
    "fta": 0,
    "ft_pct": 0.0,
    "ast": 0.0,
    "reb": 0.0,
    "oreb": 0.0,
    "dreb": 0.0,
    "stl": 0.0,
    "blk": 0.0
  },
  {
    "name": "普雷舍斯-阿丘瓦",
    "team": "国王",
    "gp": 73,
    "mpg": 23.9,
    "篮板数": 6.7,
    "进攻篮板": 2.4,
    "防守篮板": 4.3,
    "上场时间": 23.9,
    "投篮命中率": 52.8,
    "调整命中率": 55.1,
    "命中-投篮": [
      4.3,
      8.2
    ],
    "命中-三分": [
      0.4,
      1.3
    ],
    "pts": 0.0,
    "fgm": 0,
    "fga": 0,
    "fg_pct": 0.0,
    "tpm": 0,
    "tpa": 0,
    "tp_pct": 0.0,
    "ftm": 0,
    "fta": 0,
    "ft_pct": 0.0,
    "ast": 0.0,
    "reb": 0.0,
    "oreb": 0.0,
    "dreb": 0.0,
    "stl": 0.0,
    "blk": 0.0
  },
  {
    "name": "马尔科-托多洛维奇",
    "team": "鹈鹕",
    "gp": 62,
    "mpg": 14.7,
    "盖帽数": 0.87,
    "犯规数": 1.69,
    "盖帽/犯规": 0.51,
    "上场时间": 14.7,
    "pts": 0.0,
    "fgm": 0,
    "fga": 0,
    "fg_pct": 0.0,
    "tpm": 0,
    "tpa": 0,
    "tp_pct": 0.0,
    "ftm": 0,
    "fta": 0,
    "ft_pct": 0.0,
    "ast": 0.0,
    "reb": 0.0,
    "oreb": 0.0,
    "dreb": 0.0,
    "stl": 0.0,
    "blk": 0.0
  },
  {
    "name": "凯尔·菲利波夫斯基",
    "team": "爵士",
    "gp": 77,
    "mpg": 23.4,
    "篮板数": 7.2,
    "进攻篮板": 1.9,
    "防守篮板": 5.3,
    "上场时间": 23.4,
    "投篮命中率": 49.2,
    "调整命中率": 54.7,
    "命中-投篮": [
      4.2,
      8.5
    ],
    "命中-三分": [
      1.0,
      3.0
    ],
    "pts": 0.0,
    "fgm": 0,
    "fga": 0,
    "fg_pct": 0.0,
    "tpm": 0,
    "tpa": 0,
    "tp_pct": 0.0,
    "ftm": 0,
    "fta": 0,
    "ft_pct": 0.0,
    "ast": 0.0,
    "reb": 0.0,
    "oreb": 0.0,
    "dreb": 0.0,
    "stl": 0.0,
    "blk": 0.0
  },
  {
    "name": "杰里迈亚-费尔斯",
    "team": "鹈鹕",
    "gp": 82,
    "mpg": 25.8,
    "抢断数": 1.18,
    "失误数": 2.17,
    "犯规数": 1.84,
    "抢断/失误": 0.01,
    "抢断/犯规": 0.64,
    "上场时间": 25.8,
    "pts": 0.0,
    "fgm": 0,
    "fga": 0,
    "fg_pct": 0.0,
    "tpm": 0,
    "tpa": 0,
    "tp_pct": 0.0,
    "ftm": 0,
    "fta": 0,
    "ft_pct": 0.0,
    "ast": 0.0,
    "reb": 0.0,
    "oreb": 0.0,
    "dreb": 0.0,
    "stl": 0.0,
    "blk": 0.0
  },
  {
    "name": "以赛亚·科利尔",
    "team": "爵士",
    "gp": 59,
    "mpg": 25.7,
    "助攻数": 7.2,
    "失误数": 2.51,
    "助攻/失误": 2.87,
    "上场时间": 25.7,
    "抢断数": 1.12,
    "犯规数": 2.34,
    "抢断/失误": 0.01,
    "抢断/犯规": 0.48,
    "pts": 0.0,
    "fgm": 0,
    "fga": 0,
    "fg_pct": 0.0,
    "tpm": 0,
    "tpa": 0,
    "tp_pct": 0.0,
    "ftm": 0,
    "fta": 0,
    "ft_pct": 0.0,
    "ast": 0.0,
    "reb": 0.0,
    "oreb": 0.0,
    "dreb": 0.0,
    "stl": 0.0,
    "blk": 0.0
  },
  {
    "name": "贾马尔·谢德",
    "team": "猛龙",
    "gp": 82,
    "mpg": 22.6,
    "助攻数": 5.4,
    "失误数": 1.37,
    "助攻/失误": 3.94,
    "上场时间": 22.6,
    "pts": 0.0,
    "fgm": 0,
    "fga": 0,
    "fg_pct": 0.0,
    "tpm": 0,
    "tpa": 0,
    "tp_pct": 0.0,
    "ftm": 0,
    "fta": 0,
    "ft_pct": 0.0,
    "ast": 0.0,
    "reb": 0.0,
    "oreb": 0.0,
    "dreb": 0.0,
    "stl": 0.0,
    "blk": 0.0
  },
  {
    "name": "奥涅卡-奥孔古",
    "team": "老鹰",
    "gp": 74,
    "mpg": 31.0,
    "篮板数": 7.6,
    "进攻篮板": 1.9,
    "防守篮板": 5.7,
    "上场时间": 31.0,
    "抢断数": 1.11,
    "失误数": 1.72,
    "犯规数": 3.28,
    "抢断/失误": 0.01,
    "抢断/犯规": 0.34,
    "盖帽数": 1.07,
    "盖帽/犯规": 0.33,
    "pts": 0.0,
    "fgm": 0,
    "fga": 0,
    "fg_pct": 0.0,
    "tpm": 0,
    "tpa": 0,
    "tp_pct": 0.0,
    "ftm": 0,
    "fta": 0,
    "ft_pct": 0.0,
    "ast": 0.0,
    "reb": 0.0,
    "oreb": 0.0,
    "dreb": 0.0,
    "stl": 0.0,
    "blk": 0.0
  },
  {
    "name": "小海梅-哈克斯",
    "team": "热火",
    "gp": 75,
    "mpg": 28.3,
    "助攻数": 4.7,
    "失误数": 2.03,
    "助攻/失误": 2.32,
    "上场时间": 28.3,
    "投篮命中率": 50.7,
    "调整命中率": 53.9,
    "命中-投篮": [
      6.2,
      12.2
    ],
    "命中-三分": [
      0.8,
      2.4
    ],
    "pts": 0.0,
    "fgm": 0,
    "fga": 0,
    "fg_pct": 0.0,
    "tpm": 0,
    "tpa": 0,
    "tp_pct": 0.0,
    "ftm": 0,
    "fta": 0,
    "ft_pct": 0.0,
    "ast": 0.0,
    "reb": 0.0,
    "oreb": 0.0,
    "dreb": 0.0,
    "stl": 0.0,
    "blk": 0.0
  },
  {
    "name": "德里克-奎因",
    "team": "鹈鹕",
    "gp": 81,
    "mpg": 25.0,
    "篮板数": 7.1,
    "进攻篮板": 1.7,
    "防守篮板": 5.4,
    "上场时间": 25.0,
    "盖帽数": 0.91,
    "犯规数": 2.65,
    "盖帽/犯规": 0.34,
    "pts": 0.0,
    "fgm": 0,
    "fga": 0,
    "fg_pct": 0.0,
    "tpm": 0,
    "tpa": 0,
    "tp_pct": 0.0,
    "ftm": 0,
    "fta": 0,
    "ft_pct": 0.0,
    "ast": 0.0,
    "reb": 0.0,
    "oreb": 0.0,
    "dreb": 0.0,
    "stl": 0.0,
    "blk": 0.0
  },
  {
    "name": "伊夫·蜜西",
    "team": "鹈鹕",
    "gp": 66,
    "mpg": 19.7,
    "篮板数": 5.8,
    "进攻篮板": 2.8,
    "防守篮板": 3.1,
    "上场时间": 19.7,
    "盖帽数": 1.53,
    "犯规数": 1.71,
    "盖帽/犯规": 0.89,
    "pts": 0.0,
    "fgm": 0,
    "fga": 0,
    "fg_pct": 0.0,
    "tpm": 0,
    "tpa": 0,
    "tp_pct": 0.0,
    "ftm": 0,
    "fta": 0,
    "ft_pct": 0.0,
    "ast": 0.0,
    "reb": 0.0,
    "oreb": 0.0,
    "dreb": 0.0,
    "stl": 0.0,
    "blk": 0.0
  },
  {
    "name": "布赖斯·森萨博",
    "team": "爵士",
    "gp": 75,
    "mpg": 23.5,
    "罚球命中率": 82.6,
    "罚球命中数": 2.2,
    "罚球出手数": 2.7,
    "得分": 14.9,
    "上场时间": 23.5,
    "pts": 0.0,
    "fgm": 0,
    "fga": 0,
    "fg_pct": 0.0,
    "tpm": 0,
    "tpa": 0,
    "tp_pct": 0.0,
    "ftm": 0,
    "fta": 0,
    "ft_pct": 0.0,
    "ast": 0.0,
    "reb": 0.0,
    "oreb": 0.0,
    "dreb": 0.0,
    "stl": 0.0,
    "blk": 0.0
  },
  {
    "name": "阿杰·米切尔",
    "team": "雷霆",
    "gp": 57,
    "mpg": 25.8,
    "罚球命中率": 87.0,
    "罚球命中数": 2.5,
    "罚球出手数": 2.8,
    "得分": 13.6,
    "上场时间": 25.8,
    "pts": 0.0,
    "fgm": 0,
    "fga": 0,
    "fg_pct": 0.0,
    "tpm": 0,
    "tpa": 0,
    "tp_pct": 0.0,
    "ftm": 0,
    "fta": 0,
    "ft_pct": 0.0,
    "ast": 0.0,
    "reb": 0.0,
    "oreb": 0.0,
    "dreb": 0.0,
    "stl": 0.0,
    "blk": 0.0
  },
  {
    "name": "唐特-迪温琴佐",
    "team": "森林狼",
    "gp": 82,
    "mpg": 30.4,
    "助攻数": 3.8,
    "失误数": 1.44,
    "助攻/失误": 2.64,
    "上场时间": 30.4,
    "抢断数": 1.27,
    "犯规数": 2.4,
    "抢断/失误": 0.01,
    "抢断/犯规": 0.53,
    "pts": 0.0,
    "fgm": 0,
    "fga": 0,
    "fg_pct": 0.0,
    "tpm": 0,
    "tpa": 0,
    "tp_pct": 0.0,
    "ftm": 0,
    "fta": 0,
    "ft_pct": 0.0,
    "ast": 0.0,
    "reb": 0.0,
    "oreb": 0.0,
    "dreb": 0.0,
    "stl": 0.0,
    "blk": 0.0
  },
  {
    "name": "鲁迪-戈贝尔",
    "team": "森林狼",
    "gp": 76,
    "mpg": 31.3,
    "篮板数": 11.5,
    "进攻篮板": 3.9,
    "防守篮板": 7.5,
    "上场时间": 31.3,
    "盖帽数": 1.63,
    "犯规数": 2.62,
    "盖帽/犯规": 0.62,
    "投篮命中率": 68.2,
    "调整命中率": 68.3,
    "命中-投篮": [
      4.4,
      6.5
    ],
    "命中-三分": [
      0.0,
      0.1
    ],
    "pts": 0.0,
    "fgm": 0,
    "fga": 0,
    "fg_pct": 0.0,
    "tpm": 0,
    "tpa": 0,
    "tp_pct": 0.0,
    "ftm": 0,
    "fta": 0,
    "ft_pct": 0.0,
    "ast": 0.0,
    "reb": 0.0,
    "oreb": 0.0,
    "dreb": 0.0,
    "stl": 0.0,
    "blk": 0.0
  },
  {
    "name": "兰德里-沙梅特",
    "team": "尼克斯",
    "gp": 51,
    "mpg": 23.0,
    "三分命中率": 39.2,
    "三分命中数": 2.0,
    "三分出手数": 5.2,
    "得分": 9.3,
    "上场时间": 23.0,
    "pts": 0.0,
    "fgm": 0,
    "fga": 0,
    "fg_pct": 0.0,
    "tpm": 0,
    "tpa": 0,
    "tp_pct": 0.0,
    "ftm": 0,
    "fta": 0,
    "ft_pct": 0.0,
    "ast": 0.0,
    "reb": 0.0,
    "oreb": 0.0,
    "dreb": 0.0,
    "stl": 0.0,
    "blk": 0.0
  },
  {
    "name": "扎克-拉文",
    "team": "国王",
    "gp": 39,
    "mpg": 31.4,
    "三分命中率": 39.0,
    "三分命中数": 2.5,
    "三分出手数": 6.5,
    "得分": 19.2,
    "上场时间": 31.4,
    "罚球命中率": 88.0,
    "罚球命中数": 3.2,
    "罚球出手数": 3.6,
    "pts": 0.0,
    "fgm": 0,
    "fga": 0,
    "fg_pct": 0.0,
    "tpm": 0,
    "tpa": 0,
    "tp_pct": 0.0,
    "ftm": 0,
    "fta": 0,
    "ft_pct": 0.0,
    "ast": 0.0,
    "reb": 0.0,
    "oreb": 0.0,
    "dreb": 0.0,
    "stl": 0.0,
    "blk": 0.0
  },
  {
    "name": "AJ-格林",
    "team": "雄鹿",
    "gp": 78,
    "mpg": 29.1,
    "三分命中率": 41.9,
    "三分命中数": 3.0,
    "三分出手数": 7.1,
    "得分": 10.4,
    "上场时间": 29.1,
    "pts": 0.0,
    "fgm": 0,
    "fga": 0,
    "fg_pct": 0.0,
    "tpm": 0,
    "tpa": 0,
    "tp_pct": 0.0,
    "ftm": 0,
    "fta": 0,
    "ft_pct": 0.0,
    "ast": 0.0,
    "reb": 0.0,
    "oreb": 0.0,
    "dreb": 0.0,
    "stl": 0.0,
    "blk": 0.0
  },
  {
    "name": "迈尔斯-麦克布莱德",
    "team": "尼克斯",
    "gp": 41,
    "mpg": 26.3,
    "三分命中率": 41.3,
    "三分命中数": 2.7,
    "三分出手数": 6.6,
    "得分": 12.0,
    "上场时间": 26.3,
    "pts": 0.0,
    "fgm": 0,
    "fga": 0,
    "fg_pct": 0.0,
    "tpm": 0,
    "tpa": 0,
    "tp_pct": 0.0,
    "ftm": 0,
    "fta": 0,
    "ft_pct": 0.0,
    "ast": 0.0,
    "reb": 0.0,
    "oreb": 0.0,
    "dreb": 0.0,
    "stl": 0.0,
    "blk": 0.0
  },
  {
    "name": "吉米-巴特勒",
    "team": "勇士",
    "gp": 38,
    "mpg": 31.1,
    "罚球命中率": 86.4,
    "罚球命中数": 6.5,
    "罚球出手数": 7.6,
    "得分": 20.0,
    "上场时间": 31.1,
    "pts": 0.0,
    "fgm": 0,
    "fga": 0,
    "fg_pct": 0.0,
    "tpm": 0,
    "tpa": 0,
    "tp_pct": 0.0,
    "ftm": 0,
    "fta": 0,
    "ft_pct": 0.0,
    "ast": 0.0,
    "reb": 0.0,
    "oreb": 0.0,
    "dreb": 0.0,
    "stl": 0.0,
    "blk": 0.0
  },
  {
    "name": "劳里-马尔卡宁",
    "team": "爵士",
    "gp": 42,
    "mpg": 34.4,
    "罚球命中率": 89.6,
    "罚球命中数": 5.7,
    "罚球出手数": 6.4,
    "得分": 26.7,
    "上场时间": 34.4,
    "pts": 0.0,
    "fgm": 0,
    "fga": 0,
    "fg_pct": 0.0,
    "tpm": 0,
    "tpa": 0,
    "tp_pct": 0.0,
    "ftm": 0,
    "fta": 0,
    "ft_pct": 0.0,
    "ast": 0.0,
    "reb": 0.0,
    "oreb": 0.0,
    "dreb": 0.0,
    "stl": 0.0,
    "blk": 0.0
  },
  {
    "name": "迪伦-哈珀",
    "team": "马刺",
    "gp": 69,
    "mpg": 22.6,
    "助攻数": 3.9,
    "失误数": 1.43,
    "助攻/失误": 2.73,
    "上场时间": 22.6,
    "投篮命中率": 50.5,
    "调整命中率": 55.1,
    "命中-投篮": [
      4.8,
      9.5
    ],
    "命中-三分": [
      0.9,
      2.6
    ],
    "pts": 0.0,
    "fgm": 0,
    "fga": 0,
    "fg_pct": 0.0,
    "tpm": 0,
    "tpa": 0,
    "tp_pct": 0.0,
    "ftm": 0,
    "fta": 0,
    "ft_pct": 0.0,
    "ast": 0.0,
    "reb": 0.0,
    "oreb": 0.0,
    "dreb": 0.0,
    "stl": 0.0,
    "blk": 0.0
  },
  {
    "name": "贾文特-格林",
    "team": "活塞",
    "gp": 82,
    "mpg": 17.6,
    "抢断数": 1.24,
    "失误数": 0.55,
    "犯规数": 1.3,
    "抢断/失误": 0.03,
    "抢断/犯规": 0.95,
    "上场时间": 17.6,
    "pts": 0.0,
    "fgm": 0,
    "fga": 0,
    "fg_pct": 0.0,
    "tpm": 0,
    "tpa": 0,
    "tp_pct": 0.0,
    "ftm": 0,
    "fta": 0,
    "ft_pct": 0.0,
    "ast": 0.0,
    "reb": 0.0,
    "oreb": 0.0,
    "dreb": 0.0,
    "stl": 0.0,
    "blk": 0.0
  },
  {
    "name": "安德鲁-内姆布哈德",
    "team": "步行者",
    "gp": 57,
    "mpg": 31.3,
    "罚球命中率": 82.5,
    "罚球命中数": 3.4,
    "罚球出手数": 4.1,
    "得分": 16.9,
    "上场时间": 31.3,
    "pts": 0.0,
    "fgm": 0,
    "fga": 0,
    "fg_pct": 0.0,
    "tpm": 0,
    "tpa": 0,
    "tp_pct": 0.0,
    "ftm": 0,
    "fta": 0,
    "ft_pct": 0.0,
    "ast": 0.0,
    "reb": 0.0,
    "oreb": 0.0,
    "dreb": 0.0,
    "stl": 0.0,
    "blk": 0.0
  },
  {
    "name": "约什-哈特",
    "team": "尼克斯",
    "gp": 66,
    "mpg": 30.2,
    "助攻数": 4.8,
    "失误数": 1.94,
    "助攻/失误": 2.47,
    "上场时间": 30.2,
    "篮板数": 7.4,
    "进攻篮板": 1.4,
    "防守篮板": 5.9,
    "抢断数": 1.14,
    "犯规数": 2.5,
    "抢断/失误": 0.01,
    "抢断/犯规": 0.46,
    "投篮命中率": 50.8,
    "调整命中率": 59.3,
    "命中-投篮": [
      4.6,
      9.0
    ],
    "命中-三分": [
      1.5,
      3.7
    ],
    "三分命中率": 41.3,
    "三分命中数": 1.5,
    "三分出手数": 3.7,
    "得分": 12.0,
    "pts": 0.0,
    "fgm": 0,
    "fga": 0,
    "fg_pct": 0.0,
    "tpm": 0,
    "tpa": 0,
    "tp_pct": 0.0,
    "ftm": 0,
    "fta": 0,
    "ft_pct": 0.0,
    "ast": 0.0,
    "reb": 0.0,
    "oreb": 0.0,
    "dreb": 0.0,
    "stl": 0.0,
    "blk": 0.0
  },
  {
    "name": "塔里-伊森",
    "team": "火箭",
    "gp": 60,
    "mpg": 25.8,
    "篮板数": 6.3,
    "进攻篮板": 2.1,
    "防守篮板": 4.2,
    "上场时间": 25.8,
    "抢断数": 1.2,
    "失误数": 1.35,
    "犯规数": 2.3,
    "抢断/失误": 0.01,
    "抢断/犯规": 0.52,
    "pts": 0.0,
    "fgm": 0,
    "fga": 0,
    "fg_pct": 0.0,
    "tpm": 0,
    "tpa": 0,
    "tp_pct": 0.0,
    "ftm": 0,
    "fta": 0,
    "ft_pct": 0.0,
    "ast": 0.0,
    "reb": 0.0,
    "oreb": 0.0,
    "dreb": 0.0,
    "stl": 0.0,
    "blk": 0.0
  },
  {
    "name": "八村垒",
    "team": "湖人",
    "gp": 68,
    "mpg": 28.3,
    "投篮命中率": 51.4,
    "调整命中率": 61.1,
    "命中-投篮": [
      4.5,
      8.8
    ],
    "命中-三分": [
      1.7,
      3.8
    ],
    "上场时间": 28.3,
    "三分命中率": 44.3,
    "三分命中数": 1.7,
    "三分出手数": 3.8,
    "得分": 11.5,
    "pts": 0.0,
    "fgm": 0,
    "fga": 0,
    "fg_pct": 0.0,
    "tpm": 0,
    "tpa": 0,
    "tp_pct": 0.0,
    "ftm": 0,
    "fta": 0,
    "ft_pct": 0.0,
    "ast": 0.0,
    "reb": 0.0,
    "oreb": 0.0,
    "dreb": 0.0,
    "stl": 0.0,
    "blk": 0.0
  },
  {
    "name": "德文-瓦塞尔",
    "team": "马刺",
    "gp": 67,
    "mpg": 30.5,
    "三分命中率": 38.4,
    "三分命中数": 2.5,
    "三分出手数": 6.4,
    "得分": 13.9,
    "上场时间": 30.5,
    "pts": 0.0,
    "fgm": 0,
    "fga": 0,
    "fg_pct": 0.0,
    "tpm": 0,
    "tpa": 0,
    "tp_pct": 0.0,
    "ftm": 0,
    "fta": 0,
    "ft_pct": 0.0,
    "ast": 0.0,
    "reb": 0.0,
    "oreb": 0.0,
    "dreb": 0.0,
    "stl": 0.0,
    "blk": 0.0
  },
  {
    "name": "戴森-丹尼尔斯",
    "team": "老鹰",
    "gp": 76,
    "mpg": 33.2,
    "助攻数": 5.9,
    "失误数": 1.78,
    "助攻/失误": 3.31,
    "上场时间": 33.2,
    "篮板数": 6.8,
    "进攻篮板": 2.4,
    "防守篮板": 4.4,
    "抢断数": 1.96,
    "犯规数": 2.18,
    "抢断/失误": 0.01,
    "抢断/犯规": 0.9,
    "投篮命中率": 51.7,
    "调整命中率": 53.2,
    "命中-投篮": [
      5.3,
      10.2
    ],
    "命中-三分": [
      0.3,
      1.5
    ],
    "pts": 0.0,
    "fgm": 0,
    "fga": 0,
    "fg_pct": 0.0,
    "tpm": 0,
    "tpa": 0,
    "tp_pct": 0.0,
    "ftm": 0,
    "fta": 0,
    "ft_pct": 0.0,
    "ast": 0.0,
    "reb": 0.0,
    "oreb": 0.0,
    "dreb": 0.0,
    "stl": 0.0,
    "blk": 0.0
  },
  {
    "name": "奥萨尔·汤普森",
    "team": "活塞",
    "gp": 73,
    "mpg": 26.0,
    "抢断数": 2.0,
    "失误数": 1.51,
    "犯规数": 2.71,
    "抢断/失误": 0.02,
    "抢断/犯规": 0.74,
    "上场时间": 26.0,
    "盖帽数": 0.95,
    "盖帽/犯规": 0.35,
    "投篮命中率": 52.5,
    "调整命中率": 53.0,
    "命中-投篮": [
      4.2,
      7.9
    ],
    "命中-三分": [
      0.1,
      0.3
    ],
    "pts": 0.0,
    "fgm": 0,
    "fga": 0,
    "fg_pct": 0.0,
    "tpm": 0,
    "tpa": 0,
    "tp_pct": 0.0,
    "ftm": 0,
    "fta": 0,
    "ft_pct": 0.0,
    "ast": 0.0,
    "reb": 0.0,
    "oreb": 0.0,
    "dreb": 0.0,
    "stl": 0.0,
    "blk": 0.0
  },
  {
    "name": "卡梅伦-约翰逊",
    "team": "掘金",
    "gp": 54,
    "mpg": 30.5,
    "三分命中率": 43.0,
    "三分命中数": 2.0,
    "三分出手数": 4.7,
    "得分": 12.2,
    "上场时间": 30.5,
    "pts": 0.0,
    "fgm": 0,
    "fga": 0,
    "fg_pct": 0.0,
    "tpm": 0,
    "tpa": 0,
    "tp_pct": 0.0,
    "ftm": 0,
    "fta": 0,
    "ft_pct": 0.0,
    "ast": 0.0,
    "reb": 0.0,
    "oreb": 0.0,
    "dreb": 0.0,
    "stl": 0.0,
    "blk": 0.0
  },
  {
    "name": "多诺万·克林根",
    "team": "开拓者",
    "gp": 77,
    "mpg": 27.2,
    "篮板数": 11.6,
    "进攻篮板": 4.5,
    "防守篮板": 7.1,
    "上场时间": 27.2,
    "盖帽数": 1.69,
    "犯规数": 2.36,
    "盖帽/犯规": 0.72,
    "投篮命中率": 52.0,
    "调整命中率": 58.2,
    "命中-投篮": [
      4.6,
      8.9
    ],
    "命中-三分": [
      1.1,
      3.2
    ],
    "pts": 0.0,
    "fgm": 0,
    "fga": 0,
    "fg_pct": 0.0,
    "tpm": 0,
    "tpa": 0,
    "tp_pct": 0.0,
    "ftm": 0,
    "fta": 0,
    "ft_pct": 0.0,
    "ast": 0.0,
    "reb": 0.0,
    "oreb": 0.0,
    "dreb": 0.0,
    "stl": 0.0,
    "blk": 0.0
  },
  {
    "name": "斯蒂芬-库里",
    "team": "勇士",
    "gp": 43,
    "mpg": 30.9,
    "三分命中率": 39.3,
    "三分命中数": 4.4,
    "三分出手数": 11.3,
    "得分": 26.6,
    "上场时间": 30.9,
    "罚球命中率": 92.3,
    "罚球命中数": 4.7,
    "罚球出手数": 5.1,
    "pts": 0.0,
    "fgm": 0,
    "fga": 0,
    "fg_pct": 0.0,
    "tpm": 0,
    "tpa": 0,
    "tp_pct": 0.0,
    "ftm": 0,
    "fta": 0,
    "ft_pct": 0.0,
    "ast": 0.0,
    "reb": 0.0,
    "oreb": 0.0,
    "dreb": 0.0,
    "stl": 0.0,
    "blk": 0.0
  },
  {
    "name": "摩西-穆迪",
    "team": "勇士",
    "gp": 60,
    "mpg": 25.7,
    "三分命中率": 40.1,
    "三分命中数": 2.5,
    "三分出手数": 6.3,
    "得分": 12.1,
    "上场时间": 25.7,
    "pts": 0.0,
    "fgm": 0,
    "fga": 0,
    "fg_pct": 0.0,
    "tpm": 0,
    "tpa": 0,
    "tp_pct": 0.0,
    "ftm": 0,
    "fta": 0,
    "ft_pct": 0.0,
    "ast": 0.0,
    "reb": 0.0,
    "oreb": 0.0,
    "dreb": 0.0,
    "stl": 0.0,
    "blk": 0.0
  },
  {
    "name": "多米尼克-巴洛",
    "team": "76人",
    "gp": 71,
    "mpg": 23.8,
    "盖帽数": 0.75,
    "犯规数": 2.11,
    "盖帽/犯规": 0.36,
    "上场时间": 23.8,
    "pts": 0.0,
    "fgm": 0,
    "fga": 0,
    "fg_pct": 0.0,
    "tpm": 0,
    "tpa": 0,
    "tp_pct": 0.0,
    "ftm": 0,
    "fta": 0,
    "ft_pct": 0.0,
    "ast": 0.0,
    "reb": 0.0,
    "oreb": 0.0,
    "dreb": 0.0,
    "stl": 0.0,
    "blk": 0.0
  },
  {
    "name": "托拜厄斯-哈里斯",
    "team": "活塞",
    "gp": 63,
    "mpg": 27.7,
    "罚球命中率": 86.6,
    "罚球命中数": 2.2,
    "罚球出手数": 2.5,
    "得分": 13.3,
    "上场时间": 27.7,
    "pts": 0.0,
    "fgm": 0,
    "fga": 0,
    "fg_pct": 0.0,
    "tpm": 0,
    "tpa": 0,
    "tp_pct": 0.0,
    "ftm": 0,
    "fta": 0,
    "ft_pct": 0.0,
    "ast": 0.0,
    "reb": 0.0,
    "oreb": 0.0,
    "dreb": 0.0,
    "stl": 0.0,
    "blk": 0.0
  },
  {
    "name": "奥斯汀-里夫斯",
    "team": "湖人",
    "gp": 51,
    "mpg": 34.5,
    "投篮命中率": 49.0,
    "调整命中率": 56.7,
    "命中-投篮": [
      7.3,
      14.9
    ],
    "命中-三分": [
      2.3,
      6.4
    ],
    "上场时间": 34.5,
    "罚球命中率": 87.1,
    "罚球命中数": 6.3,
    "罚球出手数": 7.3,
    "得分": 23.3,
    "pts": 0.0,
    "fgm": 0,
    "fga": 0,
    "fg_pct": 0.0,
    "tpm": 0,
    "tpa": 0,
    "tp_pct": 0.0,
    "ftm": 0,
    "fta": 0,
    "ft_pct": 0.0,
    "ast": 0.0,
    "reb": 0.0,
    "oreb": 0.0,
    "dreb": 0.0,
    "stl": 0.0,
    "blk": 0.0
  },
  {
    "name": "戈加-比塔泽",
    "team": "魔术",
    "gp": 64,
    "mpg": 15.2,
    "盖帽数": 0.95,
    "犯规数": 2.13,
    "盖帽/犯规": 0.45,
    "上场时间": 15.2,
    "pts": 0.0,
    "fgm": 0,
    "fga": 0,
    "fg_pct": 0.0,
    "tpm": 0,
    "tpa": 0,
    "tp_pct": 0.0,
    "ftm": 0,
    "fta": 0,
    "ft_pct": 0.0,
    "ast": 0.0,
    "reb": 0.0,
    "oreb": 0.0,
    "dreb": 0.0,
    "stl": 0.0,
    "blk": 0.0
  },
  {
    "name": "以赛亚-斯图尔特",
    "team": "活塞",
    "gp": 58,
    "mpg": 22.7,
    "盖帽数": 1.6,
    "犯规数": 2.86,
    "盖帽/犯规": 0.56,
    "上场时间": 22.7,
    "pts": 0.0,
    "fgm": 0,
    "fga": 0,
    "fg_pct": 0.0,
    "tpm": 0,
    "tpa": 0,
    "tp_pct": 0.0,
    "ftm": 0,
    "fta": 0,
    "ft_pct": 0.0,
    "ast": 0.0,
    "reb": 0.0,
    "oreb": 0.0,
    "dreb": 0.0,
    "stl": 0.0,
    "blk": 0.0
  },
  {
    "name": "阿德姆·博纳",
    "team": "76人",
    "gp": 71,
    "mpg": 17.4,
    "盖帽数": 1.15,
    "犯规数": 2.15,
    "盖帽/犯规": 0.53,
    "上场时间": 17.4,
    "pts": 0.0,
    "fgm": 0,
    "fga": 0,
    "fg_pct": 0.0,
    "tpm": 0,
    "tpa": 0,
    "tp_pct": 0.0,
    "ftm": 0,
    "fta": 0,
    "ft_pct": 0.0,
    "ast": 0.0,
    "reb": 0.0,
    "oreb": 0.0,
    "dreb": 0.0,
    "stl": 0.0,
    "blk": 0.0
  },
  {
    "name": "贾克森-海斯",
    "team": "湖人",
    "gp": 66,
    "mpg": 18.3,
    "盖帽数": 0.79,
    "犯规数": 1.92,
    "盖帽/犯规": 0.41,
    "上场时间": 18.3,
    "pts": 0.0,
    "fgm": 0,
    "fga": 0,
    "fg_pct": 0.0,
    "tpm": 0,
    "tpa": 0,
    "tp_pct": 0.0,
    "ftm": 0,
    "fta": 0,
    "ft_pct": 0.0,
    "ast": 0.0,
    "reb": 0.0,
    "oreb": 0.0,
    "dreb": 0.0,
    "stl": 0.0,
    "blk": 0.0
  },
  {
    "name": "昆廷-格兰姆斯",
    "team": "76人",
    "gp": 75,
    "mpg": 29.4,
    "罚球命中率": 84.0,
    "罚球命中数": 2.7,
    "罚球出手数": 3.2,
    "得分": 13.4,
    "上场时间": 29.4,
    "pts": 0.0,
    "fgm": 0,
    "fga": 0,
    "fg_pct": 0.0,
    "tpm": 0,
    "tpa": 0,
    "tp_pct": 0.0,
    "ftm": 0,
    "fta": 0,
    "ft_pct": 0.0,
    "ast": 0.0,
    "reb": 0.0,
    "oreb": 0.0,
    "dreb": 0.0,
    "stl": 0.0,
    "blk": 0.0
  },
  {
    "name": "萨姆-梅里尔",
    "team": "骑士",
    "gp": 52,
    "mpg": 26.5,
    "三分命中率": 42.1,
    "三分命中数": 3.0,
    "三分出手数": 7.2,
    "得分": 12.8,
    "上场时间": 26.5,
    "pts": 0.0,
    "fgm": 0,
    "fga": 0,
    "fg_pct": 0.0,
    "tpm": 0,
    "tpa": 0,
    "tp_pct": 0.0,
    "ftm": 0,
    "fta": 0,
    "ft_pct": 0.0,
    "ast": 0.0,
    "reb": 0.0,
    "oreb": 0.0,
    "dreb": 0.0,
    "stl": 0.0,
    "blk": 0.0
  },
  {
    "name": "特雷-琼斯",
    "team": "公牛",
    "gp": 65,
    "mpg": 27.0,
    "助攻数": 5.4,
    "失误数": 1.42,
    "助攻/失误": 3.8,
    "上场时间": 27.0,
    "抢断数": 1.17,
    "犯规数": 1.45,
    "抢断/失误": 0.01,
    "抢断/犯规": 0.81,
    "投篮命中率": 55.3,
    "调整命中率": 58.6,
    "命中-投篮": [
      5.2,
      9.5
    ],
    "命中-三分": [
      0.6,
      2.0
    ],
    "罚球命中率": 84.1,
    "罚球命中数": 2.9,
    "罚球出手数": 3.5,
    "得分": 14.1,
    "pts": 0.0,
    "fgm": 0,
    "fga": 0,
    "fg_pct": 0.0,
    "tpm": 0,
    "tpa": 0,
    "tp_pct": 0.0,
    "ftm": 0,
    "fta": 0,
    "ft_pct": 0.0,
    "ast": 0.0,
    "reb": 0.0,
    "oreb": 0.0,
    "dreb": 0.0,
    "stl": 0.0,
    "blk": 0.0
  },
  {
    "name": "安德鲁-威金斯",
    "team": "热火",
    "gp": 68,
    "mpg": 30.3,
    "抢断数": 1.12,
    "失误数": 1.51,
    "犯规数": 2.29,
    "抢断/失误": 0.01,
    "抢断/犯规": 0.49,
    "上场时间": 30.3,
    "盖帽数": 1.01,
    "盖帽/犯规": 0.44,
    "三分命中率": 41.4,
    "三分命中数": 2.0,
    "三分出手数": 4.9,
    "得分": 15.4,
    "pts": 0.0,
    "fgm": 0,
    "fga": 0,
    "fg_pct": 0.0,
    "tpm": 0,
    "tpa": 0,
    "tp_pct": 0.0,
    "ftm": 0,
    "fta": 0,
    "ft_pct": 0.0,
    "ast": 0.0,
    "reb": 0.0,
    "oreb": 0.0,
    "dreb": 0.0,
    "stl": 0.0,
    "blk": 0.0
  },
  {
    "name": "约翰-科林斯",
    "team": "快船",
    "gp": 69,
    "mpg": 27.1,
    "盖帽数": 0.74,
    "犯规数": 2.71,
    "盖帽/犯规": 0.27,
    "上场时间": 27.1,
    "投篮命中率": 55.2,
    "调整命中率": 62.0,
    "命中-投篮": [
      5.3,
      9.6
    ],
    "命中-三分": [
      1.3,
      3.2
    ],
    "三分命中率": 40.6,
    "三分命中数": 1.3,
    "三分出手数": 3.2,
    "得分": 13.6,
    "pts": 0.0,
    "fgm": 0,
    "fga": 0,
    "fg_pct": 0.0,
    "tpm": 0,
    "tpa": 0,
    "tp_pct": 0.0,
    "ftm": 0,
    "fta": 0,
    "ft_pct": 0.0,
    "ast": 0.0,
    "reb": 0.0,
    "oreb": 0.0,
    "dreb": 0.0,
    "stl": 0.0,
    "blk": 0.0
  },
  {
    "name": "扬尼斯-阿德托昆博",
    "team": "雄鹿",
    "gp": 36,
    "mpg": 28.9,
    "投篮命中率": 62.4,
    "调整命中率": 63.6,
    "命中-投篮": [
      10.4,
      16.6
    ],
    "命中-三分": [
      0.4,
      1.2
    ],
    "上场时间": 28.9,
    "pts": 0.0,
    "fgm": 0,
    "fga": 0,
    "fg_pct": 0.0,
    "tpm": 0,
    "tpa": 0,
    "tp_pct": 0.0,
    "ftm": 0,
    "fta": 0,
    "ft_pct": 0.0,
    "ast": 0.0,
    "reb": 0.0,
    "oreb": 0.0,
    "dreb": 0.0,
    "stl": 0.0,
    "blk": 0.0
  },
  {
    "name": "罗伊斯-奥尼尔",
    "team": "太阳",
    "gp": 78,
    "mpg": 28.4,
    "三分命中率": 40.8,
    "三分命中数": 2.7,
    "三分出手数": 6.7,
    "得分": 9.8,
    "上场时间": 28.4,
    "pts": 0.0,
    "fgm": 0,
    "fga": 0,
    "fg_pct": 0.0,
    "tpm": 0,
    "tpa": 0,
    "tp_pct": 0.0,
    "ftm": 0,
    "fta": 0,
    "ft_pct": 0.0,
    "ast": 0.0,
    "reb": 0.0,
    "oreb": 0.0,
    "dreb": 0.0,
    "stl": 0.0,
    "blk": 0.0
  },
  {
    "name": "穆萨-迪亚巴特",
    "team": "黄蜂",
    "gp": 73,
    "mpg": 26.0,
    "篮板数": 8.7,
    "进攻篮板": 3.7,
    "防守篮板": 5.0,
    "上场时间": 26.0,
    "盖帽数": 0.99,
    "犯规数": 2.41,
    "盖帽/犯规": 0.41,
    "pts": 0.0,
    "fgm": 0,
    "fga": 0,
    "fg_pct": 0.0,
    "tpm": 0,
    "tpa": 0,
    "tp_pct": 0.0,
    "ftm": 0,
    "fta": 0,
    "ft_pct": 0.0,
    "ast": 0.0,
    "reb": 0.0,
    "oreb": 0.0,
    "dreb": 0.0,
    "stl": 0.0,
    "blk": 0.0
  },
  {
    "name": "马克西姆-雷诺",
    "team": "国王",
    "gp": 74,
    "mpg": 26.5,
    "篮板数": 7.5,
    "进攻篮板": 1.9,
    "防守篮板": 5.6,
    "上场时间": 26.5,
    "投篮命中率": 57.1,
    "调整命中率": 58.9,
    "命中-投篮": [
      5.2,
      9.1
    ],
    "命中-三分": [
      0.3,
      1.0
    ],
    "pts": 0.0,
    "fgm": 0,
    "fga": 0,
    "fg_pct": 0.0,
    "tpm": 0,
    "tpa": 0,
    "tp_pct": 0.0,
    "ftm": 0,
    "fta": 0,
    "ft_pct": 0.0,
    "ast": 0.0,
    "reb": 0.0,
    "oreb": 0.0,
    "dreb": 0.0,
    "stl": 0.0,
    "blk": 0.0
  },
  {
    "name": "凯尔登-约翰逊",
    "team": "马刺",
    "gp": 82,
    "mpg": 23.3,
    "投篮命中率": 51.9,
    "调整命中率": 58.2,
    "命中-投篮": [
      5.0,
      9.7
    ],
    "命中-三分": [
      1.2,
      3.3
    ],
    "上场时间": 23.3,
    "pts": 0.0,
    "fgm": 0,
    "fga": 0,
    "fg_pct": 0.0,
    "tpm": 0,
    "tpa": 0,
    "tp_pct": 0.0,
    "ftm": 0,
    "fta": 0,
    "ft_pct": 0.0,
    "ast": 0.0,
    "reb": 0.0,
    "oreb": 0.0,
    "dreb": 0.0,
    "stl": 0.0,
    "blk": 0.0
  },
  {
    "name": "以赛亚-乔",
    "team": "雷霆",
    "gp": 71,
    "mpg": 21.2,
    "三分命中率": 42.3,
    "三分命中数": 2.5,
    "三分出手数": 6.0,
    "得分": 11.1,
    "上场时间": 21.2,
    "pts": 0.0,
    "fgm": 0,
    "fga": 0,
    "fg_pct": 0.0,
    "tpm": 0,
    "tpa": 0,
    "tp_pct": 0.0,
    "ftm": 0,
    "fta": 0,
    "ft_pct": 0.0,
    "ast": 0.0,
    "reb": 0.0,
    "oreb": 0.0,
    "dreb": 0.0,
    "stl": 0.0,
    "blk": 0.0
  },
  {
    "name": "小贾巴里-史密斯",
    "team": "火箭",
    "gp": 77,
    "mpg": 35.1,
    "篮板数": 6.9,
    "进攻篮板": 1.4,
    "防守篮板": 5.5,
    "上场时间": 35.1,
    "盖帽数": 0.92,
    "犯规数": 2.49,
    "盖帽/犯规": 0.37,
    "pts": 0.0,
    "fgm": 0,
    "fga": 0,
    "fg_pct": 0.0,
    "tpm": 0,
    "tpa": 0,
    "tp_pct": 0.0,
    "ftm": 0,
    "fta": 0,
    "ft_pct": 0.0,
    "ast": 0.0,
    "reb": 0.0,
    "oreb": 0.0,
    "dreb": 0.0,
    "stl": 0.0,
    "blk": 0.0
  },
  {
    "name": "罗恩·霍兰二世",
    "team": "活塞",
    "gp": 78,
    "mpg": 19.9,
    "抢断数": 1.18,
    "失误数": 1.23,
    "犯规数": 2.35,
    "抢断/失误": 0.01,
    "抢断/犯规": 0.5,
    "上场时间": 19.9,
    "pts": 0.0,
    "fgm": 0,
    "fga": 0,
    "fg_pct": 0.0,
    "tpm": 0,
    "tpa": 0,
    "tp_pct": 0.0,
    "ftm": 0,
    "fta": 0,
    "ft_pct": 0.0,
    "ast": 0.0,
    "reb": 0.0,
    "oreb": 0.0,
    "dreb": 0.0,
    "stl": 0.0,
    "blk": 0.0
  },
  {
    "name": "杰登-麦克丹尼尔斯",
    "team": "森林狼",
    "gp": 73,
    "mpg": 31.7,
    "盖帽数": 1.0,
    "犯规数": 3.34,
    "盖帽/犯规": 0.3,
    "上场时间": 31.7,
    "投篮命中率": 51.5,
    "调整命中率": 57.9,
    "命中-投篮": [
      5.7,
      11.1
    ],
    "命中-三分": [
      1.4,
      3.4
    ],
    "三分命中率": 41.2,
    "三分命中数": 1.4,
    "三分出手数": 3.4,
    "得分": 14.8,
    "罚球命中率": 83.5,
    "罚球命中数": 2.0,
    "罚球出手数": 2.4,
    "pts": 0.0,
    "fgm": 0,
    "fga": 0,
    "fg_pct": 0.0,
    "tpm": 0,
    "tpa": 0,
    "tp_pct": 0.0,
    "ftm": 0,
    "fta": 0,
    "ft_pct": 0.0,
    "ast": 0.0,
    "reb": 0.0,
    "oreb": 0.0,
    "dreb": 0.0,
    "stl": 0.0,
    "blk": 0.0
  },
  {
    "name": "基扬特·乔治",
    "team": "爵士",
    "gp": 54,
    "mpg": 33.1,
    "罚球命中率": 89.2,
    "罚球命中数": 6.2,
    "罚球出手数": 7.0,
    "得分": 23.6,
    "上场时间": 33.1,
    "pts": 0.0,
    "fgm": 0,
    "fga": 0,
    "fg_pct": 0.0,
    "tpm": 0,
    "tpa": 0,
    "tp_pct": 0.0,
    "ftm": 0,
    "fta": 0,
    "ft_pct": 0.0,
    "ast": 0.0,
    "reb": 0.0,
    "oreb": 0.0,
    "dreb": 0.0,
    "stl": 0.0,
    "blk": 0.0
  },
  {
    "name": "德安德烈-艾顿",
    "team": "湖人",
    "gp": 72,
    "mpg": 27.2,
    "篮板数": 8.0,
    "进攻篮板": 2.6,
    "防守篮板": 5.4,
    "上场时间": 27.2,
    "盖帽数": 0.97,
    "犯规数": 2.18,
    "盖帽/犯规": 0.44,
    "投篮命中率": 67.1,
    "调整命中率": 67.1,
    "命中-投篮": [
      5.6,
      8.4
    ],
    "命中-三分": [
      0.0,
      0.0
    ],
    "pts": 0.0,
    "fgm": 0,
    "fga": 0,
    "fg_pct": 0.0,
    "tpm": 0,
    "tpa": 0,
    "tp_pct": 0.0,
    "ftm": 0,
    "fta": 0,
    "ft_pct": 0.0,
    "ast": 0.0,
    "reb": 0.0,
    "oreb": 0.0,
    "dreb": 0.0,
    "stl": 0.0,
    "blk": 0.0
  },
  {
    "name": "布鲁克-洛佩斯",
    "team": "快船",
    "gp": 75,
    "mpg": 21.8,
    "盖帽数": 1.16,
    "犯规数": 2.05,
    "盖帽/犯规": 0.57,
    "上场时间": 21.8,
    "pts": 0.0,
    "fgm": 0,
    "fga": 0,
    "fg_pct": 0.0,
    "tpm": 0,
    "tpa": 0,
    "tp_pct": 0.0,
    "ftm": 0,
    "fta": 0,
    "ft_pct": 0.0,
    "ast": 0.0,
    "reb": 0.0,
    "oreb": 0.0,
    "dreb": 0.0,
    "stl": 0.0,
    "blk": 0.0
  },
  {
    "name": "克林特-卡佩拉",
    "team": "火箭",
    "gp": 75,
    "mpg": 12.3,
    "盖帽数": 0.84,
    "犯规数": 0.99,
    "盖帽/犯规": 0.85,
    "上场时间": 12.3,
    "pts": 0.0,
    "fgm": 0,
    "fga": 0,
    "fg_pct": 0.0,
    "tpm": 0,
    "tpa": 0,
    "tp_pct": 0.0,
    "ftm": 0,
    "fta": 0,
    "ft_pct": 0.0,
    "ast": 0.0,
    "reb": 0.0,
    "oreb": 0.0,
    "dreb": 0.0,
    "stl": 0.0,
    "blk": 0.0
  },
  {
    "name": "弗朗茨-瓦格纳",
    "team": "魔术",
    "gp": 34,
    "mpg": 30.0,
    "罚球命中率": 82.3,
    "罚球命中数": 4.8,
    "罚球出手数": 5.8,
    "得分": 20.6,
    "上场时间": 30.0,
    "pts": 0.0,
    "fgm": 0,
    "fga": 0,
    "fg_pct": 0.0,
    "tpm": 0,
    "tpa": 0,
    "tp_pct": 0.0,
    "ftm": 0,
    "fta": 0,
    "ft_pct": 0.0,
    "ast": 0.0,
    "reb": 0.0,
    "oreb": 0.0,
    "dreb": 0.0,
    "stl": 0.0,
    "blk": 0.0
  },
  {
    "name": "邓肯-罗宾逊",
    "team": "活塞",
    "gp": 77,
    "mpg": 27.4,
    "三分命中率": 41.0,
    "三分命中数": 2.9,
    "三分出手数": 7.0,
    "得分": 12.2,
    "上场时间": 27.4,
    "pts": 0.0,
    "fgm": 0,
    "fga": 0,
    "fg_pct": 0.0,
    "tpm": 0,
    "tpa": 0,
    "tp_pct": 0.0,
    "ftm": 0,
    "fta": 0,
    "ft_pct": 0.0,
    "ast": 0.0,
    "reb": 0.0,
    "oreb": 0.0,
    "dreb": 0.0,
    "stl": 0.0,
    "blk": 0.0
  },
  {
    "name": "内米亚斯-克塔",
    "team": "凯尔特人",
    "gp": 76,
    "mpg": 25.3,
    "篮板数": 8.4,
    "进攻篮板": 3.0,
    "防守篮板": 5.3,
    "上场时间": 25.3,
    "盖帽数": 1.32,
    "犯规数": 2.84,
    "盖帽/犯规": 0.46,
    "投篮命中率": 65.3,
    "调整命中率": 65.4,
    "命中-投篮": [
      4.3,
      6.6
    ],
    "命中-三分": [
      0.0,
      0.1
    ],
    "pts": 0.0,
    "fgm": 0,
    "fga": 0,
    "fg_pct": 0.0,
    "tpm": 0,
    "tpa": 0,
    "tp_pct": 0.0,
    "ftm": 0,
    "fta": 0,
    "ft_pct": 0.0,
    "ast": 0.0,
    "reb": 0.0,
    "oreb": 0.0,
    "dreb": 0.0,
    "stl": 0.0,
    "blk": 0.0
  },
  {
    "name": "萨姆-豪瑟",
    "team": "凯尔特人",
    "gp": 78,
    "mpg": 24.8,
    "三分命中率": 39.3,
    "三分命中数": 2.5,
    "三分出手数": 6.5,
    "得分": 9.2,
    "上场时间": 24.8,
    "pts": 0.0,
    "fgm": 0,
    "fga": 0,
    "fg_pct": 0.0,
    "tpm": 0,
    "tpa": 0,
    "tp_pct": 0.0,
    "ftm": 0,
    "fta": 0,
    "ft_pct": 0.0,
    "ast": 0.0,
    "reb": 0.0,
    "oreb": 0.0,
    "dreb": 0.0,
    "stl": 0.0,
    "blk": 0.0
  },
  {
    "name": "安东尼·布莱克",
    "team": "魔术",
    "gp": 64,
    "mpg": 29.8,
    "抢断数": 1.42,
    "失误数": 2.06,
    "犯规数": 2.66,
    "抢断/失误": 0.01,
    "抢断/犯规": 0.53,
    "上场时间": 29.8,
    "pts": 0.0,
    "fgm": 0,
    "fga": 0,
    "fg_pct": 0.0,
    "tpm": 0,
    "tpa": 0,
    "tp_pct": 0.0,
    "ftm": 0,
    "fta": 0,
    "ft_pct": 0.0,
    "ast": 0.0,
    "reb": 0.0,
    "oreb": 0.0,
    "dreb": 0.0,
    "stl": 0.0,
    "blk": 0.0
  },
  {
    "name": "保罗-里德",
    "team": "活塞",
    "gp": 65,
    "mpg": 13.9,
    "盖帽数": 0.92,
    "犯规数": 1.85,
    "盖帽/犯规": 0.5,
    "上场时间": 13.9,
    "pts": 0.0,
    "fgm": 0,
    "fga": 0,
    "fg_pct": 0.0,
    "tpm": 0,
    "tpa": 0,
    "tp_pct": 0.0,
    "ftm": 0,
    "fta": 0,
    "ft_pct": 0.0,
    "ast": 0.0,
    "reb": 0.0,
    "oreb": 0.0,
    "dreb": 0.0,
    "stl": 0.0,
    "blk": 0.0
  },
  {
    "name": "小迈克尔-波特",
    "team": "篮网",
    "gp": 52,
    "mpg": 32.5,
    "罚球命中率": 85.9,
    "罚球命中数": 3.8,
    "罚球出手数": 4.4,
    "得分": 24.2,
    "上场时间": 32.5,
    "pts": 0.0,
    "fgm": 0,
    "fga": 0,
    "fg_pct": 0.0,
    "tpm": 0,
    "tpa": 0,
    "tp_pct": 0.0,
    "ftm": 0,
    "fta": 0,
    "ft_pct": 0.0,
    "ast": 0.0,
    "reb": 0.0,
    "oreb": 0.0,
    "dreb": 0.0,
    "stl": 0.0,
    "blk": 0.0
  },
  {
    "name": "桑德罗-马穆凯拉什维利",
    "team": "猛龙",
    "gp": 80,
    "mpg": 21.9,
    "投篮命中率": 52.3,
    "调整命中率": 61.5,
    "命中-投篮": [
      4.1,
      7.9
    ],
    "命中-三分": [
      1.4,
      3.7
    ],
    "上场时间": 21.9,
    "三分命中率": 38.9,
    "三分命中数": 1.4,
    "三分出手数": 3.7,
    "得分": 11.2,
    "pts": 0.0,
    "fgm": 0,
    "fga": 0,
    "fg_pct": 0.0,
    "tpm": 0,
    "tpa": 0,
    "tp_pct": 0.0,
    "ftm": 0,
    "fta": 0,
    "ft_pct": 0.0,
    "ast": 0.0,
    "reb": 0.0,
    "oreb": 0.0,
    "dreb": 0.0,
    "stl": 0.0,
    "blk": 0.0
  },
  {
    "name": "里德·谢泼德",
    "team": "火箭",
    "gp": 82,
    "mpg": 26.2,
    "抢断数": 1.49,
    "失误数": 1.5,
    "犯规数": 2.02,
    "抢断/失误": 0.01,
    "抢断/犯规": 0.74,
    "上场时间": 26.2,
    "三分命中率": 39.4,
    "三分命中数": 2.8,
    "三分出手数": 7.0,
    "得分": 13.5,
    "pts": 0.0,
    "fgm": 0,
    "fga": 0,
    "fg_pct": 0.0,
    "tpm": 0,
    "tpa": 0,
    "tp_pct": 0.0,
    "ftm": 0,
    "fta": 0,
    "ft_pct": 0.0,
    "ast": 0.0,
    "reb": 0.0,
    "oreb": 0.0,
    "dreb": 0.0,
    "stl": 0.0,
    "blk": 0.0
  },
  {
    "name": "丹尼斯·詹金斯",
    "team": "活塞",
    "gp": 72,
    "mpg": 20.2,
    "助攻数": 3.9,
    "失误数": 1.6,
    "助攻/失误": 2.44,
    "上场时间": 20.2,
    "罚球命中率": 83.2,
    "罚球命中数": 1.9,
    "罚球出手数": 2.2,
    "得分": 9.3,
    "pts": 0.0,
    "fgm": 0,
    "fga": 0,
    "fg_pct": 0.0,
    "tpm": 0,
    "tpa": 0,
    "tp_pct": 0.0,
    "ftm": 0,
    "fta": 0,
    "ft_pct": 0.0,
    "ast": 0.0,
    "reb": 0.0,
    "oreb": 0.0,
    "dreb": 0.0,
    "stl": 0.0,
    "blk": 0.0
  },
  {
    "name": "安德烈-德拉蒙德",
    "team": "76人",
    "gp": 63,
    "mpg": 19.5,
    "篮板数": 8.4,
    "进攻篮板": 3.2,
    "防守篮板": 5.3,
    "上场时间": 19.5,
    "盖帽数": 0.78,
    "犯规数": 1.98,
    "盖帽/犯规": 0.39,
    "pts": 0.0,
    "fgm": 0,
    "fga": 0,
    "fg_pct": 0.0,
    "tpm": 0,
    "tpa": 0,
    "tp_pct": 0.0,
    "ftm": 0,
    "fta": 0,
    "ft_pct": 0.0,
    "ast": 0.0,
    "reb": 0.0,
    "oreb": 0.0,
    "dreb": 0.0,
    "stl": 0.0,
    "blk": 0.0
  },
  {
    "name": "马利克-蒙克",
    "team": "国王",
    "gp": 62,
    "mpg": 22.0,
    "三分命中率": 39.5,
    "三分命中数": 2.0,
    "三分出手数": 5.1,
    "得分": 12.5,
    "上场时间": 22.0,
    "pts": 0.0,
    "fgm": 0,
    "fga": 0,
    "fg_pct": 0.0,
    "tpm": 0,
    "tpa": 0,
    "tp_pct": 0.0,
    "ftm": 0,
    "fta": 0,
    "ft_pct": 0.0,
    "ast": 0.0,
    "reb": 0.0,
    "oreb": 0.0,
    "dreb": 0.0,
    "stl": 0.0,
    "blk": 0.0
  },
  {
    "name": "戴罗恩-夏普",
    "team": "篮网",
    "gp": 62,
    "mpg": 18.7,
    "篮板数": 6.7,
    "进攻篮板": 2.8,
    "防守篮板": 3.9,
    "上场时间": 18.7,
    "pts": 0.0,
    "fgm": 0,
    "fga": 0,
    "fg_pct": 0.0,
    "tpm": 0,
    "tpa": 0,
    "tp_pct": 0.0,
    "ftm": 0,
    "fta": 0,
    "ft_pct": 0.0,
    "ast": 0.0,
    "reb": 0.0,
    "oreb": 0.0,
    "dreb": 0.0,
    "stl": 0.0,
    "blk": 0.0
  },
  {
    "name": "马库斯-斯马特",
    "team": "湖人",
    "gp": 62,
    "mpg": 28.5,
    "抢断数": 1.4,
    "失误数": 1.48,
    "犯规数": 2.61,
    "抢断/失误": 0.02,
    "抢断/犯规": 0.54,
    "上场时间": 28.5,
    "pts": 0.0,
    "fgm": 0,
    "fga": 0,
    "fg_pct": 0.0,
    "tpm": 0,
    "tpa": 0,
    "tp_pct": 0.0,
    "ftm": 0,
    "fta": 0,
    "ft_pct": 0.0,
    "ast": 0.0,
    "reb": 0.0,
    "oreb": 0.0,
    "dreb": 0.0,
    "stl": 0.0,
    "blk": 0.0
  },
  {
    "name": "塞德里克-考沃德",
    "team": "灰熊",
    "gp": 62,
    "mpg": 25.8,
    "篮板数": 5.9,
    "进攻篮板": 1.3,
    "防守篮板": 4.5,
    "上场时间": 25.8,
    "罚球命中率": 84.3,
    "罚球命中数": 2.3,
    "罚球出手数": 2.7,
    "得分": 13.6,
    "pts": 0.0,
    "fgm": 0,
    "fga": 0,
    "fg_pct": 0.0,
    "tpm": 0,
    "tpa": 0,
    "tp_pct": 0.0,
    "ftm": 0,
    "fta": 0,
    "ft_pct": 0.0,
    "ast": 0.0,
    "reb": 0.0,
    "oreb": 0.0,
    "dreb": 0.0,
    "stl": 0.0,
    "blk": 0.0
  },
  {
    "name": "科林-吉莱斯皮",
    "team": "太阳",
    "gp": 80,
    "mpg": 28.5,
    "助攻数": 4.6,
    "失误数": 1.56,
    "助攻/失误": 2.95,
    "上场时间": 28.5,
    "抢断数": 1.24,
    "犯规数": 1.63,
    "抢断/失误": 0.01,
    "抢断/犯规": 0.76,
    "三分命中率": 40.1,
    "三分命中数": 2.9,
    "三分出手数": 7.2,
    "得分": 12.7,
    "pts": 0.0,
    "fgm": 0,
    "fga": 0,
    "fg_pct": 0.0,
    "tpm": 0,
    "tpa": 0,
    "tp_pct": 0.0,
    "ftm": 0,
    "fta": 0,
    "ft_pct": 0.0,
    "ast": 0.0,
    "reb": 0.0,
    "oreb": 0.0,
    "dreb": 0.0,
    "stl": 0.0,
    "blk": 0.0
  },
  {
    "name": "贝勒·沙伊尔曼",
    "team": "凯尔特人",
    "gp": 77,
    "mpg": 18.6,
    "三分命中率": 39.9,
    "三分命中数": 1.3,
    "三分出手数": 3.2,
    "得分": 5.5,
    "上场时间": 18.6,
    "pts": 0.0,
    "fgm": 0,
    "fga": 0,
    "fg_pct": 0.0,
    "tpm": 0,
    "tpa": 0,
    "tp_pct": 0.0,
    "ftm": 0,
    "fta": 0,
    "ft_pct": 0.0,
    "ast": 0.0,
    "reb": 0.0,
    "oreb": 0.0,
    "dreb": 0.0,
    "stl": 0.0,
    "blk": 0.0
  },
  {
    "name": "乔尔-恩比德",
    "team": "76人",
    "gp": 38,
    "mpg": 31.6,
    "投篮命中率": 48.9,
    "调整命中率": 52.7,
    "命中-投篮": [
      9.0,
      18.3
    ],
    "命中-三分": [
      1.4,
      4.2
    ],
    "上场时间": 31.6,
    "罚球命中率": 85.4,
    "罚球命中数": 7.5,
    "罚球出手数": 8.8,
    "得分": 26.9,
    "pts": 0.0,
    "fgm": 0,
    "fga": 0,
    "fg_pct": 0.0,
    "tpm": 0,
    "tpa": 0,
    "tp_pct": 0.0,
    "ftm": 0,
    "fta": 0,
    "ft_pct": 0.0,
    "ast": 0.0,
    "reb": 0.0,
    "oreb": 0.0,
    "dreb": 0.0,
    "stl": 0.0,
    "blk": 0.0
  },
  {
    "name": "德雷蒙德-格林",
    "team": "勇士",
    "gp": 68,
    "mpg": 27.5,
    "助攻数": 5.5,
    "失误数": 2.66,
    "助攻/失误": 2.07,
    "上场时间": 27.5,
    "pts": 0.0,
    "fgm": 0,
    "fga": 0,
    "fg_pct": 0.0,
    "tpm": 0,
    "tpa": 0,
    "tp_pct": 0.0,
    "ftm": 0,
    "fta": 0,
    "ft_pct": 0.0,
    "ast": 0.0,
    "reb": 0.0,
    "oreb": 0.0,
    "dreb": 0.0,
    "stl": 0.0,
    "blk": 0.0
  },
  {
    "name": "米切尔-罗宾逊",
    "team": "尼克斯",
    "gp": 60,
    "mpg": 19.6,
    "篮板数": 8.8,
    "进攻篮板": 4.2,
    "防守篮板": 4.6,
    "上场时间": 19.6,
    "盖帽数": 1.17,
    "犯规数": 2.12,
    "盖帽/犯规": 0.55,
    "pts": 0.0,
    "fgm": 0,
    "fga": 0,
    "fg_pct": 0.0,
    "tpm": 0,
    "tpa": 0,
    "tp_pct": 0.0,
    "ftm": 0,
    "fta": 0,
    "ft_pct": 0.0,
    "ast": 0.0,
    "reb": 0.0,
    "oreb": 0.0,
    "dreb": 0.0,
    "stl": 0.0,
    "blk": 0.0
  },
  {
    "name": "RJ-巴雷特",
    "team": "猛龙",
    "gp": 57,
    "mpg": 30.3,
    "投篮命中率": 49.1,
    "调整命中率": 55.0,
    "命中-投篮": [
      7.0,
      14.3
    ],
    "命中-三分": [
      1.7,
      5.0
    ],
    "上场时间": 30.3,
    "pts": 0.0,
    "fgm": 0,
    "fga": 0,
    "fg_pct": 0.0,
    "tpm": 0,
    "tpa": 0,
    "tp_pct": 0.0,
    "ftm": 0,
    "fta": 0,
    "ft_pct": 0.0,
    "ast": 0.0,
    "reb": 0.0,
    "oreb": 0.0,
    "dreb": 0.0,
    "stl": 0.0,
    "blk": 0.0
  },
  {
    "name": "小蒂姆-哈达威",
    "team": "掘金",
    "gp": 80,
    "mpg": 26.6,
    "三分命中率": 40.7,
    "三分命中数": 2.8,
    "三分出手数": 6.9,
    "得分": 13.5,
    "上场时间": 26.6,
    "pts": 0.0,
    "fgm": 0,
    "fga": 0,
    "fg_pct": 0.0,
    "tpm": 0,
    "tpa": 0,
    "tp_pct": 0.0,
    "ftm": 0,
    "fta": 0,
    "ft_pct": 0.0,
    "ast": 0.0,
    "reb": 0.0,
    "oreb": 0.0,
    "dreb": 0.0,
    "stl": 0.0,
    "blk": 0.0
  },
  {
    "name": "迈尔斯-特纳",
    "team": "雄鹿",
    "gp": 71,
    "mpg": 26.9,
    "盖帽数": 1.62,
    "犯规数": 2.61,
    "盖帽/犯规": 0.62,
    "上场时间": 26.9,
    "pts": 0.0,
    "fgm": 0,
    "fga": 0,
    "fg_pct": 0.0,
    "tpm": 0,
    "tpa": 0,
    "tp_pct": 0.0,
    "ftm": 0,
    "fta": 0,
    "ft_pct": 0.0,
    "ast": 0.0,
    "reb": 0.0,
    "oreb": 0.0,
    "dreb": 0.0,
    "stl": 0.0,
    "blk": 0.0
  },
  {
    "name": "米卡尔-布里奇斯",
    "team": "尼克斯",
    "gp": 82,
    "mpg": 32.8,
    "抢断数": 1.3,
    "失误数": 1.01,
    "犯规数": 1.95,
    "抢断/失误": 0.02,
    "抢断/犯规": 0.67,
    "上场时间": 32.8,
    "盖帽数": 0.76,
    "盖帽/犯规": 0.39,
    "投篮命中率": 49.0,
    "调整命中率": 57.2,
    "命中-投篮": [
      5.8,
      11.7
    ],
    "命中-三分": [
      1.9,
      5.1
    ],
    "pts": 0.0,
    "fgm": 0,
    "fga": 0,
    "fg_pct": 0.0,
    "tpm": 0,
    "tpa": 0,
    "tp_pct": 0.0,
    "ftm": 0,
    "fta": 0,
    "ft_pct": 0.0,
    "ast": 0.0,
    "reb": 0.0,
    "oreb": 0.0,
    "dreb": 0.0,
    "stl": 0.0,
    "blk": 0.0
  },
  {
    "name": "布兰登-威廉姆斯",
    "team": "独行侠",
    "gp": 66,
    "mpg": 22.2,
    "助攻数": 3.9,
    "失误数": 1.89,
    "助攻/失误": 2.06,
    "上场时间": 22.2,
    "pts": 0.0,
    "fgm": 0,
    "fga": 0,
    "fg_pct": 0.0,
    "tpm": 0,
    "tpa": 0,
    "tp_pct": 0.0,
    "ftm": 0,
    "fta": 0,
    "ft_pct": 0.0,
    "ast": 0.0,
    "reb": 0.0,
    "oreb": 0.0,
    "dreb": 0.0,
    "stl": 0.0,
    "blk": 0.0
  },
  {
    "name": "尼古拉斯-克拉克斯顿",
    "team": "篮网",
    "gp": 69,
    "mpg": 27.8,
    "篮板数": 6.9,
    "进攻篮板": 2.4,
    "防守篮板": 4.5,
    "上场时间": 27.8,
    "盖帽数": 1.12,
    "犯规数": 2.29,
    "盖帽/犯规": 0.49,
    "投篮命中率": 57.1,
    "调整命中率": 57.4,
    "命中-投篮": [
      4.8,
      8.4
    ],
    "命中-三分": [
      0.0,
      0.3
    ],
    "pts": 0.0,
    "fgm": 0,
    "fga": 0,
    "fg_pct": 0.0,
    "tpm": 0,
    "tpa": 0,
    "tp_pct": 0.0,
    "ftm": 0,
    "fta": 0,
    "ft_pct": 0.0,
    "ast": 0.0,
    "reb": 0.0,
    "oreb": 0.0,
    "dreb": 0.0,
    "stl": 0.0,
    "blk": 0.0
  },
  {
    "name": "小凯文-波特",
    "team": "雄鹿",
    "gp": 38,
    "mpg": 33.2,
    "罚球命中率": 87.8,
    "罚球命中数": 3.6,
    "罚球出手数": 4.1,
    "得分": 17.4,
    "上场时间": 33.2,
    "pts": 0.0,
    "fgm": 0,
    "fga": 0,
    "fg_pct": 0.0,
    "tpm": 0,
    "tpa": 0,
    "tp_pct": 0.0,
    "ftm": 0,
    "fta": 0,
    "ft_pct": 0.0,
    "ast": 0.0,
    "reb": 0.0,
    "oreb": 0.0,
    "dreb": 0.0,
    "stl": 0.0,
    "blk": 0.0
  },
  {
    "name": "叶戈尔-杰明",
    "team": "篮网",
    "gp": 52,
    "mpg": 25.2,
    "三分命中率": 38.5,
    "三分命中数": 2.4,
    "三分出手数": 6.2,
    "得分": 10.3,
    "上场时间": 25.2,
    "pts": 0.0,
    "fgm": 0,
    "fga": 0,
    "fg_pct": 0.0,
    "tpm": 0,
    "tpa": 0,
    "tp_pct": 0.0,
    "ftm": 0,
    "fta": 0,
    "ft_pct": 0.0,
    "ast": 0.0,
    "reb": 0.0,
    "oreb": 0.0,
    "dreb": 0.0,
    "stl": 0.0,
    "blk": 0.0
  },
  {
    "name": "图马尼-卡马拉",
    "team": "开拓者",
    "gp": 82,
    "mpg": 33.3,
    "抢断数": 1.15,
    "失误数": 1.76,
    "犯规数": 2.89,
    "抢断/失误": 0.01,
    "抢断/犯规": 0.4,
    "上场时间": 33.3,
    "pts": 0.0,
    "fgm": 0,
    "fga": 0,
    "fg_pct": 0.0,
    "tpm": 0,
    "tpa": 0,
    "tp_pct": 0.0,
    "ftm": 0,
    "fta": 0,
    "ft_pct": 0.0,
    "ast": 0.0,
    "reb": 0.0,
    "oreb": 0.0,
    "dreb": 0.0,
    "stl": 0.0,
    "blk": 0.0
  },
  {
    "name": "尼古拉斯-巴图姆",
    "team": "快船",
    "gp": 74,
    "mpg": 17.5,
    "三分命中率": 40.4,
    "三分命中数": 1.2,
    "三分出手数": 3.1,
    "得分": 4.0,
    "上场时间": 17.5,
    "pts": 0.0,
    "fgm": 0,
    "fga": 0,
    "fg_pct": 0.0,
    "tpm": 0,
    "tpa": 0,
    "tp_pct": 0.0,
    "ftm": 0,
    "fta": 0,
    "ft_pct": 0.0,
    "ast": 0.0,
    "reb": 0.0,
    "oreb": 0.0,
    "dreb": 0.0,
    "stl": 0.0,
    "blk": 0.0
  },
  {
    "name": "威尔-理查德",
    "team": "勇士",
    "gp": 69,
    "mpg": 20.0,
    "抢断数": 1.16,
    "失误数": 0.77,
    "犯规数": 1.9,
    "抢断/失误": 0.02,
    "抢断/犯规": 0.61,
    "上场时间": 20.0,
    "pts": 0.0,
    "fgm": 0,
    "fga": 0,
    "fg_pct": 0.0,
    "tpm": 0,
    "tpa": 0,
    "tp_pct": 0.0,
    "ftm": 0,
    "fta": 0,
    "ft_pct": 0.0,
    "ast": 0.0,
    "reb": 0.0,
    "oreb": 0.0,
    "dreb": 0.0,
    "stl": 0.0,
    "blk": 0.0
  },
  {
    "name": "卡森·华莱士",
    "team": "雷霆",
    "gp": 77,
    "mpg": 26.6,
    "抢断数": 1.95,
    "失误数": 0.95,
    "犯规数": 2.0,
    "抢断/失误": 0.03,
    "抢断/犯规": 0.97,
    "上场时间": 26.6,
    "pts": 0.0,
    "fgm": 0,
    "fga": 0,
    "fg_pct": 0.0,
    "tpm": 0,
    "tpa": 0,
    "tp_pct": 0.0,
    "ftm": 0,
    "fta": 0,
    "ft_pct": 0.0,
    "ast": 0.0,
    "reb": 0.0,
    "oreb": 0.0,
    "dreb": 0.0,
    "stl": 0.0,
    "blk": 0.0
  },
  {
    "name": "戴维恩-米切尔",
    "team": "热火",
    "gp": 70,
    "mpg": 28.6,
    "助攻数": 6.5,
    "失误数": 1.54,
    "助攻/失误": 4.22,
    "上场时间": 28.6,
    "三分命中率": 39.5,
    "三分命中数": 1.3,
    "三分出手数": 3.3,
    "得分": 9.3,
    "pts": 0.0,
    "fgm": 0,
    "fga": 0,
    "fg_pct": 0.0,
    "tpm": 0,
    "tpa": 0,
    "tp_pct": 0.0,
    "ftm": 0,
    "fta": 0,
    "ft_pct": 0.0,
    "ast": 0.0,
    "reb": 0.0,
    "oreb": 0.0,
    "dreb": 0.0,
    "stl": 0.0,
    "blk": 0.0
  },
  {
    "name": "杰隆·泰森",
    "team": "骑士",
    "gp": 66,
    "mpg": 26.9,
    "投篮命中率": 49.3,
    "调整命中率": 59.2,
    "命中-投篮": [
      5.0,
      10.1
    ],
    "命中-三分": [
      2.0,
      4.5
    ],
    "上场时间": 26.9,
    "三分命中率": 44.6,
    "三分命中数": 2.0,
    "三分出手数": 4.5,
    "得分": 13.2,
    "pts": 0.0,
    "fgm": 0,
    "fga": 0,
    "fg_pct": 0.0,
    "tpm": 0,
    "tpa": 0,
    "tp_pct": 0.0,
    "ftm": 0,
    "fta": 0,
    "ft_pct": 0.0,
    "ast": 0.0,
    "reb": 0.0,
    "oreb": 0.0,
    "dreb": 0.0,
    "stl": 0.0,
    "blk": 0.0
  },
  {
    "name": "杰-胡夫",
    "team": "步行者",
    "gp": 82,
    "mpg": 21.0,
    "盖帽数": 1.87,
    "犯规数": 2.39,
    "盖帽/犯规": 0.78,
    "上场时间": 21.0,
    "pts": 0.0,
    "fgm": 0,
    "fga": 0,
    "fg_pct": 0.0,
    "tpm": 0,
    "tpa": 0,
    "tp_pct": 0.0,
    "ftm": 0,
    "fta": 0,
    "ft_pct": 0.0,
    "ast": 0.0,
    "reb": 0.0,
    "oreb": 0.0,
    "dreb": 0.0,
    "stl": 0.0,
    "blk": 0.0
  }
]